{
  "generate 16384i64": {
    "runtimes": [
      2251992,
      2246924,
      2247181,
      2249334,
      2250789,
      2255402,
      2264136,
      2262120,
      2260612,
      2256004
    ]
  },
  "generate 8192i64": {
    "runtimes": [
      300657,
      328355,
      332237,
      332267,
      333299,
      331870,
      323129,
      334422,
      331529,
      319465
    ]
  },
  "generate 4096i64": {
    "runtimes": [
      48903,
      48229,
      48586,
      48405,
      48868,
      48619,
      48534,
      48407,
      49207,
      48481
    ]
  },
  "generate 2048i64": {
    "runtimes": [
      12334,
      12041,
      11946,
      11992,
      12070,
      12056,
      12060,
      12163,
      12013,
      11982
    ]
  }
}
