{
  "generate 2048i64": {
    "bytes": 33554432,
    "runtimes": [
      27656,
      27571,
      28271,
      28272,
      28300,
      28345,
      28243,
      28256,
      28247,
      28215
    ]
  },
  "generate 4096i64": {
    "bytes": 134217728,
    "runtimes": [
      69505,
      69319,
      69296,
      69281,
      69266,
      69305,
      69261,
      69262,
      68876,
      85251
    ]
  },
  "generate 8192i64": {
    "bytes": 536870912,
    "runtimes": [
      301444,
      284039,
      315068,
      318554,
      311845,
      269545,
      325721,
      314255,
      301864,
      318143
    ]
  },
  "generate 16384i64": {
    "bytes": 2147483648,
    "runtimes": [
      1424462,
      1358799,
      1406612,
      1438828,
      1362984,
      1379503,
      1407676,
      1419186,
      1374175,
      1375897
    ]
  },
  "generate 32768i64": {
    "bytes": 8589934592,
    "runtimes": [
      9502757,
      9443471,
      9456745,
      9504779,
      9509128,
      9507784,
      9514769,
      9492505,
      9527652,
      9541610
    ]
  }
}
