{"bfast.fut":{"datasets":{"bfast-data/gargantuan.in":{"bytes":{"device":11520019200},"runtimes":[116867,76324,70370,70682,70708,70716,70679,70667,70670,70708,70665,70747,70654,70684,70713,70696,70651,70698,70692,70707,70661,70687,70625,70655,70650,70662,70598,70674,70723,70614,70685,70686,70709,70695,70662,70635,70684,70706,70652,70688,70665,70627,70677,70690,70703,70696,70732,70682,70729,70719,70720,70697,70761,70691,70701,70643,70714,70654,70699,70626,70661,70679,70687,70687,70606,70591,70615,70642,70689,70672,70613,70687,70713,70683,70682,70678,70607,70683,70612,70652,70682,70652,70683,70689,70693,70672,70592,70632,70681,70656,70633,70698,70678,70672,70629,70657,70668,70639,70637,70664],"stderr":"Compared main.suff_outer_par_0 <= 300000: false.\nCompared main.suff_outer_par_1 <= 2400000: false.\nCompared main.suff_outer_par_2 <= 19200000: true.\nCompared main.suff_intra_par_3 <= 128: true.\nCompared main.suff_intra_par_4 <= 128: true.\nCompared main.suff_outer_par_5 <= 300000: true.\nCompared main.suff_outer_par_6 <= 2400000: true.\nCompared main.suff_outer_par_7 <= 300000: true.\nCompared main.suff_outer_par_8 <= 2400000: false.\nCompared main.suff_outer_par_9 <= 300000: false.\nCompared main.suff_outer_par_10 <= 480000000: true.\nCompared main.suff_intra_par_11 <= 1600: true.\nCompared main.suff_outer_par_12 <= 300000: false.\nCompared main.suff_intra_par_13 <= 400: true.\nCompared main.suff_outer_par_14 <= 300000: true.\nCompared main.suff_intra_par_15 <= 1200: true.\nruntime: 116867\n\nCompared main.suff_outer_par_0 <= 300000: false.\nCompared main.suff_outer_par_1 <= 2400000: false.\nCompared main.suff_outer_par_2 <= 19200000: true.\nCompared main.suff_intra_par_3 <= 128: true.\nCompared main.suff_intra_par_4 <= 128: true.\nCompared main.suff_outer_par_5 <= 300000: true.\nCompared main.suff_outer_par_6 <= 2400000: true.\nCompared main.suff_outer_par_7 <= 300000: true.\nCompared main.suff_outer_par_8 <= 2400000: false.\nCompared main.suff_outer_par_9 <= 300000: false.\nCompared main.suff_outer_par_10 <= 480000000: true.\nCompared main.suff_intra_par_11 <= 1600: true.\nCompared main.suff_outer_par_12 <= 300000: false.\nCompared main.suff_intra_par_13 <= 400: true.\nCompared main.suff_outer_par_14 <= 300000: true.\nCompared main.suff_intra_par_15 <= 1200: true.\nruntime: 76324\n\nCompared main.suff_outer_par_0 <= 300000: false.\nCompared main.suff_outer_par_1 <= 2400000: false.\nCompared main.suff_outer_par_2 <= 19200000: true.\nCompared main.suff_intra_par_3 <= 128: true.\nCompared main.suff_intra_par_4 <= 128: true.\nCompared main.suff_outer_par_5 <= 300000: true.\nCompared main.suff_outer_par_6 <= 2400000: true.\nCompared main.suff_outer_par_7 <= 300000: true.\nCompared main.suff_outer_par_8 <= 2400000: false.\nCompared main.suff_outer_par_9 <= 300000: false.\nCompared main.suff_outer_par_10 <= 480000000: true.\nCompared main.suff_intra_par_11 <= 1600: true.\nCompared main.suff_outer_par_12 <= 300000: false.\nCompared main.suff_intra_par_13 <= 400: true.\nCompared main.suff_outer_par_14 <= 300000: true.\nCompared main.suff_intra_par_15 <= 1200: true.\nruntime: 70370\n\nCompared main.suff_outer_par_0 <= 300000: false.\nCompared main.suff_outer_par_1 <= 2400000: false.\nCompared main.suff_outer_par_2 <= 19200000: true.\nCompared main.suff_intra_par_3 <= 128: true.\nCompared main.suff_intra_par_4 <= 128: true.\nCompared main.suff_outer_par_5 <= 300000: true.\nCompared main.suff_outer_par_6 <= 2400000: true.\nCompared main.suff_outer_par_7 <= 300000: true.\nCompared main.suff_outer_par_8 <= 2400000: false.\nCompared main.suff_outer_par_9 <= 300000: false.\nCompared main.suff_outer_par_10 <= 480000000: true.\nCompared main.suff_intra_par_11 <= 1600: true.\nCompared main.suff_outer_par_12 <= 300000: false.\nCompared main.suff_intra_par_13 <= 400: true.\nCompared main.suff_outer_par_14 <= 300000: true.\nCompared main.suff_intra_par_15 <= 1200: true.\nruntime: 70682\n\nCompared main.suff_outer_par_0 <= 300000: false.\nCompared main.suff_outer_par_1 <= 2400000: false.\nCompared main.suff_outer_par_2 <= 19200000: true.\nCompared main.suff_intra_par_3 <= 128: true.\nCompared main.suff_intra_par_4 <= 128: true.\nCompared main.suff_outer_par_5 <= 300000: true.\nCompared main.suff_outer_par_6 <= 2400000: true.\nCompared main.suff_outer_par_7 <= 300000: true.\nCompared main.suff_outer_par_8 <= 2400000: false.\nCompared main.suff_outer_par_9 <= 300000: false.\nCompared main.suff_outer_par_10 <= 480000000: true.\nCompared main.suff_intra_par_11 <= 1600: true.\nCompared main.suff_outer_par_12 <= 300000: false.\nCompared main.suff_intra_par_13 <= 400: true.\nCompared main.suff_outer_par_14 <= 300000: true.\nCompared main.suff_intra_par_15 <= 1200: true.\nruntime: 70708\n\nCompared main.suff_outer_par_0 <= 300000: false.\nCompared main.suff_outer_par_1 <= 2400000: false.\nCompared main.suff_outer_par_2 <= 19200000: true.\nCompared main.suff_intra_par_3 <= 128: true.\nCompared main.suff_intra_par_4 <= 128: true.\nCompared main.suff_outer_par_5 <= 300000: true.\nCompared main.suff_outer_par_6 <= 2400000: true.\nCompared main.suff_outer_par_7 <= 300000: true.\nCompared main.suff_outer_par_8 <= 2400000: false.\nCompared main.suff_outer_par_9 <= 300000: false.\nCompared main.suff_outer_par_10 <= 480000000: true.\nCompared main.suff_intra_par_11 <= 1600: true.\nCompared main.suff_outer_par_12 <= 300000: false.\nCompared main.suff_intra_par_13 <= 400: true.\nCompared main.suff_outer_par_14 <= 300000: true.\nCompared main.suff_intra_par_15 <= 1200: true.\nruntime: 70716\n\nCompared main.suff_outer_par_0 <= 300000: false.\nCompared main.suff_outer_par_1 <= 2400000: false.\nCompared main.suff_outer_par_2 <= 19200000: true.\nCompared main.suff_intra_par_3 <= 128: true.\nCompared main.suff_intra_par_4 <= 128: true.\nCompared main.suff_outer_par_5 <= 300000: true.\nCompared main.suff_outer_par_6 <= 2400000: true.\nCompared main.suff_outer_par_7 <= 300000: true.\nCompared main.suff_outer_par_8 <= 2400000: false.\nCompared main.suff_outer_par_9 <= 300000: false.\nCompared main.suff_outer_par_10 <= 480000000: true.\nCompared main.suff_intra_par_11 <= 1600: true.\nCompared main.suff_outer_par_12 <= 300000: false.\nCompared main.suff_intra_par_13 <= 400: true.\nCompared main.suff_outer_par_14 <= 300000: true.\nCompared main.suff_intra_par_15 <= 1200: true.\nruntime: 70679\n\nCompared main.suff_outer_par_0 <= 300000: false.\nCompared main.suff_outer_par_1 <= 2400000: false.\nCompared main.suff_outer_par_2 <= 19200000: true.\nCompared main.suff_intra_par_3 <= 128: true.\nCompared main.suff_intra_par_4 <= 128: true.\nCompared main.suff_outer_par_5 <= 300000: true.\nCompared main.suff_outer_par_6 <= 2400000: true.\nCompared main.suff_outer_par_7 <= 300000: true.\nCompared main.suff_outer_par_8 <= 2400000: false.\nCompared main.suff_outer_par_9 <= 300000: false.\nCompared main.suff_outer_par_10 <= 480000000: true.\nCompared main.suff_intra_par_11 <= 1600: true.\nCompared main.suff_outer_par_12 <= 300000: false.\nCompared main.suff_intra_par_13 <= 400: true.\nCompared main.suff_outer_par_14 <= 300000: true.\nCompared main.suff_intra_par_15 <= 1200: true.\nruntime: 70667\n\nCompared main.suff_outer_par_0 <= 300000: false.\nCompared main.suff_outer_par_1 <= 2400000: false.\nCompared main.suff_outer_par_2 <= 19200000: true.\nCompared main.suff_intra_par_3 <= 128: true.\nCompared main.suff_intra_par_4 <= 128: true.\nCompared main.suff_outer_par_5 <= 300000: true.\nCompared main.suff_outer_par_6 <= 2400000: true.\nCompared main.suff_outer_par_7 <= 300000: true.\nCompared main.suff_outer_par_8 <= 2400000: false.\nCompared main.suff_outer_par_9 <= 300000: false.\nCompared main.suff_outer_par_10 <= 480000000: true.\nCompared main.suff_intra_par_11 <= 1600: true.\nCompared main.suff_outer_par_12 <= 300000: false.\nCompared main.suff_intra_par_13 <= 400: true.\nCompared main.suff_outer_par_14 <= 300000: true.\nCompared main.suff_intra_par_15 <= 1200: true.\nruntime: 70670\n\nCompared main.suff_outer_par_0 <= 300000: false.\nCompared main.suff_outer_par_1 <= 2400000: false.\nCompared main.suff_outer_par_2 <= 19200000: true.\nCompared main.suff_intra_par_3 <= 128: true.\nCompared main.suff_intra_par_4 <= 128: true.\nCompared main.suff_outer_par_5 <= 300000: true.\nCompared main.suff_outer_par_6 <= 2400000: true.\nCompared main.suff_outer_par_7 <= 300000: true.\nCompared main.suff_outer_par_8 <= 2400000: false.\nCompared main.suff_outer_par_9 <= 300000: false.\nCompared main.suff_outer_par_10 <= 480000000: true.\nCompared main.suff_intra_par_11 <= 1600: true.\nCompared main.suff_outer_par_12 <= 300000: false.\nCompared main.suff_intra_par_13 <= 400: true.\nCompared main.suff_outer_par_14 <= 300000: true.\nCompared main.suff_intra_par_15 <= 1200: true.\nruntime: 70708\n\nCompared main.suff_outer_par_0 <= 300000: false.\nCompared main.suff_outer_par_1 <= 2400000: false.\nCompared main.suff_outer_par_2 <= 19200000: true.\nCompared main.suff_intra_par_3 <= 128: true.\nCompared main.suff_intra_par_4 <= 128: true.\nCompared main.suff_outer_par_5 <= 300000: true.\nCompared main.suff_outer_par_6 <= 2400000: true.\nCompared main.suff_outer_par_7 <= 300000: true.\nCompared main.suff_outer_par_8 <= 2400000: false.\nCompared main.suff_outer_par_9 <= 300000: false.\nCompared main.suff_outer_par_10 <= 480000000: true.\nCompared main.suff_intra_par_11 <= 1600: true.\nCompared main.suff_outer_par_12 <= 300000: false.\nCompared main.suff_intra_par_13 <= 400: true.\nCompared main.suff_outer_par_14 <= 300000: true.\nCompared main.suff_intra_par_15 <= 1200: true.\nruntime: 70665\n\nCompared main.suff_outer_par_0 <= 300000: false.\nCompared main.suff_outer_par_1 <= 2400000: false.\nCompared main.suff_outer_par_2 <= 19200000: true.\nCompared main.suff_intra_par_3 <= 128: true.\nCompared main.suff_intra_par_4 <= 128: true.\nCompared main.suff_outer_par_5 <= 300000: true.\nCompared main.suff_outer_par_6 <= 2400000: true.\nCompared main.suff_outer_par_7 <= 300000: true.\nCompared main.suff_outer_par_8 <= 2400000: false.\nCompared main.suff_outer_par_9 <= 300000: false.\nCompared main.suff_outer_par_10 <= 480000000: true.\nCompared main.suff_intra_par_11 <= 1600: true.\nCompared main.suff_outer_par_12 <= 300000: false.\nCompared main.suff_intra_par_13 <= 400: true.\nCompared main.suff_outer_par_14 <= 300000: true.\nCompared main.suff_intra_par_15 <= 1200: true.\nruntime: 70747\n\nCompared main.suff_outer_par_0 <= 300000: false.\nCompared main.suff_outer_par_1 <= 2400000: false.\nCompared main.suff_outer_par_2 <= 19200000: true.\nCompared main.suff_intra_par_3 <= 128: true.\nCompared main.suff_intra_par_4 <= 128: true.\nCompared main.suff_outer_par_5 <= 300000: true.\nCompared main.suff_outer_par_6 <= 2400000: true.\nCompared main.suff_outer_par_7 <= 300000: true.\nCompared main.suff_outer_par_8 <= 2400000: false.\nCompared main.suff_outer_par_9 <= 300000: false.\nCompared main.suff_outer_par_10 <= 480000000: true.\nCompared main.suff_intra_par_11 <= 1600: true.\nCompared main.suff_outer_par_12 <= 300000: false.\nCompared main.suff_intra_par_13 <= 400: true.\nCompared main.suff_outer_par_14 <= 300000: true.\nCompared main.suff_intra_par_15 <= 1200: true.\nruntime: 70654\n\nCompared main.suff_outer_par_0 <= 300000: false.\nCompared main.suff_outer_par_1 <= 2400000: false.\nCompared main.suff_outer_par_2 <= 19200000: true.\nCompared main.suff_intra_par_3 <= 128: true.\nCompared main.suff_intra_par_4 <= 128: true.\nCompared main.suff_outer_par_5 <= 300000: true.\nCompared main.suff_outer_par_6 <= 2400000: true.\nCompared main.suff_outer_par_7 <= 300000: true.\nCompared main.suff_outer_par_8 <= 2400000: false.\nCompared main.suff_outer_par_9 <= 300000: false.\nCompared main.suff_outer_par_10 <= 480000000: true.\nCompared main.suff_intra_par_11 <= 1600: true.\nCompared main.suff_outer_par_12 <= 300000: false.\nCompared main.suff_intra_par_13 <= 400: true.\nCompared main.suff_outer_par_14 <= 300000: true.\nCompared main.suff_intra_par_15 <= 1200: true.\nruntime: 70684\n\nCompared main.suff_outer_par_0 <= 300000: false.\nCompared main.suff_outer_par_1 <= 2400000: false.\nCompared main.suff_outer_par_2 <= 19200000: true.\nCompared main.suff_intra_par_3 <= 128: true.\nCompared main.suff_intra_par_4 <= 128: true.\nCompared main.suff_outer_par_5 <= 300000: true.\nCompared main.suff_outer_par_6 <= 2400000: true.\nCompared main.suff_outer_par_7 <= 300000: true.\nCompared main.suff_outer_par_8 <= 2400000: false.\nCompared main.suff_outer_par_9 <= 300000: false.\nCompared main.suff_outer_par_10 <= 480000000: true.\nCompared main.suff_intra_par_11 <= 1600: true.\nCompared main.suff_outer_par_12 <= 300000: false.\nCompared main.suff_intra_par_13 <= 400: true.\nCompared main.suff_outer_par_14 <= 300000: true.\nCompared main.suff_intra_par_15 <= 1200: true.\nruntime: 70713\n\nCompared main.suff_outer_par_0 <= 300000: false.\nCompared main.suff_outer_par_1 <= 2400000: false.\nCompared main.suff_outer_par_2 <= 19200000: true.\nCompared main.suff_intra_par_3 <= 128: true.\nCompared main.suff_intra_par_4 <= 128: true.\nCompared main.suff_outer_par_5 <= 300000: true.\nCompared main.suff_outer_par_6 <= 2400000: true.\nCompared main.suff_outer_par_7 <= 300000: true.\nCompared main.suff_outer_par_8 <= 2400000: false.\nCompared main.suff_outer_par_9 <= 300000: false.\nCompared main.suff_outer_par_10 <= 480000000: true.\nCompared main.suff_intra_par_11 <= 1600: true.\nCompared main.suff_outer_par_12 <= 300000: false.\nCompared main.suff_intra_par_13 <= 400: true.\nCompared main.suff_outer_par_14 <= 300000: true.\nCompared main.suff_intra_par_15 <= 1200: true.\nruntime: 70696\n\nCompared main.suff_outer_par_0 <= 300000: false.\nCompared main.suff_outer_par_1 <= 2400000: false.\nCompared main.suff_outer_par_2 <= 19200000: true.\nCompared main.suff_intra_par_3 <= 128: true.\nCompared main.suff_intra_par_4 <= 128: true.\nCompared main.suff_outer_par_5 <= 300000: true.\nCompared main.suff_outer_par_6 <= 2400000: true.\nCompared main.suff_outer_par_7 <= 300000: true.\nCompared main.suff_outer_par_8 <= 2400000: false.\nCompared main.suff_outer_par_9 <= 300000: false.\nCompared main.suff_outer_par_10 <= 480000000: true.\nCompared main.suff_intra_par_11 <= 1600: true.\nCompared main.suff_outer_par_12 <= 300000: false.\nCompared main.suff_intra_par_13 <= 400: true.\nCompared main.suff_outer_par_14 <= 300000: true.\nCompared main.suff_intra_par_15 <= 1200: true.\nruntime: 70651\n\nCompared main.suff_outer_par_0 <= 300000: false.\nCompared main.suff_outer_par_1 <= 2400000: false.\nCompared main.suff_outer_par_2 <= 19200000: true.\nCompared main.suff_intra_par_3 <= 128: true.\nCompared main.suff_intra_par_4 <= 128: true.\nCompared main.suff_outer_par_5 <= 300000: true.\nCompared main.suff_outer_par_6 <= 2400000: true.\nCompared main.suff_outer_par_7 <= 300000: true.\nCompared main.suff_outer_par_8 <= 2400000: false.\nCompared main.suff_outer_par_9 <= 300000: false.\nCompared main.suff_outer_par_10 <= 480000000: true.\nCompared main.suff_intra_par_11 <= 1600: true.\nCompared main.suff_outer_par_12 <= 300000: false.\nCompared main.suff_intra_par_13 <= 400: true.\nCompared main.suff_outer_par_14 <= 300000: true.\nCompared main.suff_intra_par_15 <= 1200: true.\nruntime: 70698\n\nCompared main.suff_outer_par_0 <= 300000: false.\nCompared main.suff_outer_par_1 <= 2400000: false.\nCompared main.suff_outer_par_2 <= 19200000: true.\nCompared main.suff_intra_par_3 <= 128: true.\nCompared main.suff_intra_par_4 <= 128: true.\nCompared main.suff_outer_par_5 <= 300000: true.\nCompared main.suff_outer_par_6 <= 2400000: true.\nCompared main.suff_outer_par_7 <= 300000: true.\nCompared main.suff_outer_par_8 <= 2400000: false.\nCompared main.suff_outer_par_9 <= 300000: false.\nCompared main.suff_outer_par_10 <= 480000000: true.\nCompared main.suff_intra_par_11 <= 1600: true.\nCompared main.suff_outer_par_12 <= 300000: false.\nCompared main.suff_intra_par_13 <= 400: true.\nCompared main.suff_outer_par_14 <= 300000: true.\nCompared main.suff_intra_par_15 <= 1200: true.\nruntime: 70692\n\nCompared main.suff_outer_par_0 <= 300000: false.\nCompared main.suff_outer_par_1 <= 2400000: false.\nCompared main.suff_outer_par_2 <= 19200000: true.\nCompared main.suff_intra_par_3 <= 128: true.\nCompared main.suff_intra_par_4 <= 128: true.\nCompared main.suff_outer_par_5 <= 300000: true.\nCompared main.suff_outer_par_6 <= 2400000: true.\nCompared main.suff_outer_par_7 <= 300000: true.\nCompared main.suff_outer_par_8 <= 2400000: false.\nCompared main.suff_outer_par_9 <= 300000: false.\nCompared main.suff_outer_par_10 <= 480000000: true.\nCompared main.suff_intra_par_11 <= 1600: true.\nCompared main.suff_outer_par_12 <= 300000: false.\nCompared main.suff_intra_par_13 <= 400: true.\nCompared main.suff_outer_par_14 <= 300000: true.\nCompared main.suff_intra_par_15 <= 1200: true.\nruntime: 70707\n\nCompared main.suff_outer_par_0 <= 300000: false.\nCompared main.suff_outer_par_1 <= 2400000: false.\nCompared main.suff_outer_par_2 <= 19200000: true.\nCompared main.suff_intra_par_3 <= 128: true.\nCompared main.suff_intra_par_4 <= 128: true.\nCompared main.suff_outer_par_5 <= 300000: true.\nCompared main.suff_outer_par_6 <= 2400000: true.\nCompared main.suff_outer_par_7 <= 300000: true.\nCompared main.suff_outer_par_8 <= 2400000: false.\nCompared main.suff_outer_par_9 <= 300000: false.\nCompared main.suff_outer_par_10 <= 480000000: true.\nCompared main.suff_intra_par_11 <= 1600: true.\nCompared main.suff_outer_par_12 <= 300000: false.\nCompared main.suff_intra_par_13 <= 400: true.\nCompared main.suff_outer_par_14 <= 300000: true.\nCompared main.suff_intra_par_15 <= 1200: true.\nruntime: 70661\n\nCompared main.suff_outer_par_0 <= 300000: false.\nCompared main.suff_outer_par_1 <= 2400000: false.\nCompared main.suff_outer_par_2 <= 19200000: true.\nCompared main.suff_intra_par_3 <= 128: true.\nCompared main.suff_intra_par_4 <= 128: true.\nCompared main.suff_outer_par_5 <= 300000: true.\nCompared main.suff_outer_par_6 <= 2400000: true.\nCompared main.suff_outer_par_7 <= 300000: true.\nCompared main.suff_outer_par_8 <= 2400000: false.\nCompared main.suff_outer_par_9 <= 300000: false.\nCompared main.suff_outer_par_10 <= 480000000: true.\nCompared main.suff_intra_par_11 <= 1600: true.\nCompared main.suff_outer_par_12 <= 300000: false.\nCompared main.suff_intra_par_13 <= 400: true.\nCompared main.suff_outer_par_14 <= 300000: true.\nCompared main.suff_intra_par_15 <= 1200: true.\nruntime: 70687\n\nCompared main.suff_outer_par_0 <= 300000: false.\nCompared main.suff_outer_par_1 <= 2400000: false.\nCompared main.suff_outer_par_2 <= 19200000: true.\nCompared main.suff_intra_par_3 <= 128: true.\nCompared main.suff_intra_par_4 <= 128: true.\nCompared main.suff_outer_par_5 <= 300000: true.\nCompared main.suff_outer_par_6 <= 2400000: true.\nCompared main.suff_outer_par_7 <= 300000: true.\nCompared main.suff_outer_par_8 <= 2400000: false.\nCompared main.suff_outer_par_9 <= 300000: false.\nCompared main.suff_outer_par_10 <= 480000000: true.\nCompared main.suff_intra_par_11 <= 1600: true.\nCompared main.suff_outer_par_12 <= 300000: false.\nCompared main.suff_intra_par_13 <= 400: true.\nCompared main.suff_outer_par_14 <= 300000: true.\nCompared main.suff_intra_par_15 <= 1200: true.\nruntime: 70625\n\nCompared main.suff_outer_par_0 <= 300000: false.\nCompared main.suff_outer_par_1 <= 2400000: false.\nCompared main.suff_outer_par_2 <= 19200000: true.\nCompared main.suff_intra_par_3 <= 128: true.\nCompared main.suff_intra_par_4 <= 128: true.\nCompared main.suff_outer_par_5 <= 300000: true.\nCompared main.suff_outer_par_6 <= 2400000: true.\nCompared main.suff_outer_par_7 <= 300000: true.\nCompared main.suff_outer_par_8 <= 2400000: false.\nCompared main.suff_outer_par_9 <= 300000: false.\nCompared main.suff_outer_par_10 <= 480000000: true.\nCompared main.suff_intra_par_11 <= 1600: true.\nCompared main.suff_outer_par_12 <= 300000: false.\nCompared main.suff_intra_par_13 <= 400: true.\nCompared main.suff_outer_par_14 <= 300000: true.\nCompared main.suff_intra_par_15 <= 1200: true.\nruntime: 70655\n\nCompared main.suff_outer_par_0 <= 300000: false.\nCompared main.suff_outer_par_1 <= 2400000: false.\nCompared main.suff_outer_par_2 <= 19200000: true.\nCompared main.suff_intra_par_3 <= 128: true.\nCompared main.suff_intra_par_4 <= 128: true.\nCompared main.suff_outer_par_5 <= 300000: true.\nCompared main.suff_outer_par_6 <= 2400000: true.\nCompared main.suff_outer_par_7 <= 300000: true.\nCompared main.suff_outer_par_8 <= 2400000: false.\nCompared main.suff_outer_par_9 <= 300000: false.\nCompared main.suff_outer_par_10 <= 480000000: true.\nCompared main.suff_intra_par_11 <= 1600: true.\nCompared main.suff_outer_par_12 <= 300000: false.\nCompared main.suff_intra_par_13 <= 400: true.\nCompared main.suff_outer_par_14 <= 300000: true.\nCompared main.suff_intra_par_15 <= 1200: true.\nruntime: 70650\n\nCompared main.suff_outer_par_0 <= 300000: false.\nCompared main.suff_outer_par_1 <= 2400000: false.\nCompared main.suff_outer_par_2 <= 19200000: true.\nCompared main.suff_intra_par_3 <= 128: true.\nCompared main.suff_intra_par_4 <= 128: true.\nCompared main.suff_outer_par_5 <= 300000: true.\nCompared main.suff_outer_par_6 <= 2400000: true.\nCompared main.suff_outer_par_7 <= 300000: true.\nCompared main.suff_outer_par_8 <= 2400000: false.\nCompared main.suff_outer_par_9 <= 300000: false.\nCompared main.suff_outer_par_10 <= 480000000: true.\nCompared main.suff_intra_par_11 <= 1600: true.\nCompared main.suff_outer_par_12 <= 300000: false.\nCompared main.suff_intra_par_13 <= 400: true.\nCompared main.suff_outer_par_14 <= 300000: true.\nCompared main.suff_intra_par_15 <= 1200: true.\nruntime: 70662\n\nCompared main.suff_outer_par_0 <= 300000: false.\nCompared main.suff_outer_par_1 <= 2400000: false.\nCompared main.suff_outer_par_2 <= 19200000: true.\nCompared main.suff_intra_par_3 <= 128: true.\nCompared main.suff_intra_par_4 <= 128: true.\nCompared main.suff_outer_par_5 <= 300000: true.\nCompared main.suff_outer_par_6 <= 2400000: true.\nCompared main.suff_outer_par_7 <= 300000: true.\nCompared main.suff_outer_par_8 <= 2400000: false.\nCompared main.suff_outer_par_9 <= 300000: false.\nCompared main.suff_outer_par_10 <= 480000000: true.\nCompared main.suff_intra_par_11 <= 1600: true.\nCompared main.suff_outer_par_12 <= 300000: false.\nCompared main.suff_intra_par_13 <= 400: true.\nCompared main.suff_outer_par_14 <= 300000: true.\nCompared main.suff_intra_par_15 <= 1200: true.\nruntime: 70598\n\nCompared main.suff_outer_par_0 <= 300000: false.\nCompared main.suff_outer_par_1 <= 2400000: false.\nCompared main.suff_outer_par_2 <= 19200000: true.\nCompared main.suff_intra_par_3 <= 128: true.\nCompared main.suff_intra_par_4 <= 128: true.\nCompared main.suff_outer_par_5 <= 300000: true.\nCompared main.suff_outer_par_6 <= 2400000: true.\nCompared main.suff_outer_par_7 <= 300000: true.\nCompared main.suff_outer_par_8 <= 2400000: false.\nCompared main.suff_outer_par_9 <= 300000: false.\nCompared main.suff_outer_par_10 <= 480000000: true.\nCompared main.suff_intra_par_11 <= 1600: true.\nCompared main.suff_outer_par_12 <= 300000: false.\nCompared main.suff_intra_par_13 <= 400: true.\nCompared main.suff_outer_par_14 <= 300000: true.\nCompared main.suff_intra_par_15 <= 1200: true.\nruntime: 70674\n\nCompared main.suff_outer_par_0 <= 300000: false.\nCompared main.suff_outer_par_1 <= 2400000: false.\nCompared main.suff_outer_par_2 <= 19200000: true.\nCompared main.suff_intra_par_3 <= 128: true.\nCompared main.suff_intra_par_4 <= 128: true.\nCompared main.suff_outer_par_5 <= 300000: true.\nCompared main.suff_outer_par_6 <= 2400000: true.\nCompared main.suff_outer_par_7 <= 300000: true.\nCompared main.suff_outer_par_8 <= 2400000: false.\nCompared main.suff_outer_par_9 <= 300000: false.\nCompared main.suff_outer_par_10 <= 480000000: true.\nCompared main.suff_intra_par_11 <= 1600: true.\nCompared main.suff_outer_par_12 <= 300000: false.\nCompared main.suff_intra_par_13 <= 400: true.\nCompared main.suff_outer_par_14 <= 300000: true.\nCompared main.suff_intra_par_15 <= 1200: true.\nruntime: 70723\n\nCompared main.suff_outer_par_0 <= 300000: false.\nCompared main.suff_outer_par_1 <= 2400000: false.\nCompared main.suff_outer_par_2 <= 19200000: true.\nCompared main.suff_intra_par_3 <= 128: true.\nCompared main.suff_intra_par_4 <= 128: true.\nCompared main.suff_outer_par_5 <= 300000: true.\nCompared main.suff_outer_par_6 <= 2400000: true.\nCompared main.suff_outer_par_7 <= 300000: true.\nCompared main.suff_outer_par_8 <= 2400000: false.\nCompared main.suff_outer_par_9 <= 300000: false.\nCompared main.suff_outer_par_10 <= 480000000: true.\nCompared main.suff_intra_par_11 <= 1600: true.\nCompared main.suff_outer_par_12 <= 300000: false.\nCompared main.suff_intra_par_13 <= 400: true.\nCompared main.suff_outer_par_14 <= 300000: true.\nCompared main.suff_intra_par_15 <= 1200: true.\nruntime: 70614\n\nCompared main.suff_outer_par_0 <= 300000: false.\nCompared main.suff_outer_par_1 <= 2400000: false.\nCompared main.suff_outer_par_2 <= 19200000: true.\nCompared main.suff_intra_par_3 <= 128: true.\nCompared main.suff_intra_par_4 <= 128: true.\nCompared main.suff_outer_par_5 <= 300000: true.\nCompared main.suff_outer_par_6 <= 2400000: true.\nCompared main.suff_outer_par_7 <= 300000: true.\nCompared main.suff_outer_par_8 <= 2400000: false.\nCompared main.suff_outer_par_9 <= 300000: false.\nCompared main.suff_outer_par_10 <= 480000000: true.\nCompared main.suff_intra_par_11 <= 1600: true.\nCompared main.suff_outer_par_12 <= 300000: false.\nCompared main.suff_intra_par_13 <= 400: true.\nCompared main.suff_outer_par_14 <= 300000: true.\nCompared main.suff_intra_par_15 <= 1200: true.\nruntime: 70685\n\nCompared main.suff_outer_par_0 <= 300000: false.\nCompared main.suff_outer_par_1 <= 2400000: false.\nCompared main.suff_outer_par_2 <= 19200000: true.\nCompared main.suff_intra_par_3 <= 128: true.\nCompared main.suff_intra_par_4 <= 128: true.\nCompared main.suff_outer_par_5 <= 300000: true.\nCompared main.suff_outer_par_6 <= 2400000: true.\nCompared main.suff_outer_par_7 <= 300000: true.\nCompared main.suff_outer_par_8 <= 2400000: false.\nCompared main.suff_outer_par_9 <= 300000: false.\nCompared main.suff_outer_par_10 <= 480000000: true.\nCompared main.suff_intra_par_11 <= 1600: true.\nCompared main.suff_outer_par_12 <= 300000: false.\nCompared main.suff_intra_par_13 <= 400: true.\nCompared main.suff_outer_par_14 <= 300000: true.\nCompared main.suff_intra_par_15 <= 1200: true.\nruntime: 70686\n\nCompared main.suff_outer_par_0 <= 300000: false.\nCompared main.suff_outer_par_1 <= 2400000: false.\nCompared main.suff_outer_par_2 <= 19200000: true.\nCompared main.suff_intra_par_3 <= 128: true.\nCompared main.suff_intra_par_4 <= 128: true.\nCompared main.suff_outer_par_5 <= 300000: true.\nCompared main.suff_outer_par_6 <= 2400000: true.\nCompared main.suff_outer_par_7 <= 300000: true.\nCompared main.suff_outer_par_8 <= 2400000: false.\nCompared main.suff_outer_par_9 <= 300000: false.\nCompared main.suff_outer_par_10 <= 480000000: true.\nCompared main.suff_intra_par_11 <= 1600: true.\nCompared main.suff_outer_par_12 <= 300000: false.\nCompared main.suff_intra_par_13 <= 400: true.\nCompared main.suff_outer_par_14 <= 300000: true.\nCompared main.suff_intra_par_15 <= 1200: true.\nruntime: 70709\n\nCompared main.suff_outer_par_0 <= 300000: false.\nCompared main.suff_outer_par_1 <= 2400000: false.\nCompared main.suff_outer_par_2 <= 19200000: true.\nCompared main.suff_intra_par_3 <= 128: true.\nCompared main.suff_intra_par_4 <= 128: true.\nCompared main.suff_outer_par_5 <= 300000: true.\nCompared main.suff_outer_par_6 <= 2400000: true.\nCompared main.suff_outer_par_7 <= 300000: true.\nCompared main.suff_outer_par_8 <= 2400000: false.\nCompared main.suff_outer_par_9 <= 300000: false.\nCompared main.suff_outer_par_10 <= 480000000: true.\nCompared main.suff_intra_par_11 <= 1600: true.\nCompared main.suff_outer_par_12 <= 300000: false.\nCompared main.suff_intra_par_13 <= 400: true.\nCompared main.suff_outer_par_14 <= 300000: true.\nCompared main.suff_intra_par_15 <= 1200: true.\nruntime: 70695\n\nCompared main.suff_outer_par_0 <= 300000: false.\nCompared main.suff_outer_par_1 <= 2400000: false.\nCompared main.suff_outer_par_2 <= 19200000: true.\nCompared main.suff_intra_par_3 <= 128: true.\nCompared main.suff_intra_par_4 <= 128: true.\nCompared main.suff_outer_par_5 <= 300000: true.\nCompared main.suff_outer_par_6 <= 2400000: true.\nCompared main.suff_outer_par_7 <= 300000: true.\nCompared main.suff_outer_par_8 <= 2400000: false.\nCompared main.suff_outer_par_9 <= 300000: false.\nCompared main.suff_outer_par_10 <= 480000000: true.\nCompared main.suff_intra_par_11 <= 1600: true.\nCompared main.suff_outer_par_12 <= 300000: false.\nCompared main.suff_intra_par_13 <= 400: true.\nCompared main.suff_outer_par_14 <= 300000: true.\nCompared main.suff_intra_par_15 <= 1200: true.\nruntime: 70662\n\nCompared main.suff_outer_par_0 <= 300000: false.\nCompared main.suff_outer_par_1 <= 2400000: false.\nCompared main.suff_outer_par_2 <= 19200000: true.\nCompared main.suff_intra_par_3 <= 128: true.\nCompared main.suff_intra_par_4 <= 128: true.\nCompared main.suff_outer_par_5 <= 300000: true.\nCompared main.suff_outer_par_6 <= 2400000: true.\nCompared main.suff_outer_par_7 <= 300000: true.\nCompared main.suff_outer_par_8 <= 2400000: false.\nCompared main.suff_outer_par_9 <= 300000: false.\nCompared main.suff_outer_par_10 <= 480000000: true.\nCompared main.suff_intra_par_11 <= 1600: true.\nCompared main.suff_outer_par_12 <= 300000: false.\nCompared main.suff_intra_par_13 <= 400: true.\nCompared main.suff_outer_par_14 <= 300000: true.\nCompared main.suff_intra_par_15 <= 1200: true.\nruntime: 70635\n\nCompared main.suff_outer_par_0 <= 300000: false.\nCompared main.suff_outer_par_1 <= 2400000: false.\nCompared main.suff_outer_par_2 <= 19200000: true.\nCompared main.suff_intra_par_3 <= 128: true.\nCompared main.suff_intra_par_4 <= 128: true.\nCompared main.suff_outer_par_5 <= 300000: true.\nCompared main.suff_outer_par_6 <= 2400000: true.\nCompared main.suff_outer_par_7 <= 300000: true.\nCompared main.suff_outer_par_8 <= 2400000: false.\nCompared main.suff_outer_par_9 <= 300000: false.\nCompared main.suff_outer_par_10 <= 480000000: true.\nCompared main.suff_intra_par_11 <= 1600: true.\nCompared main.suff_outer_par_12 <= 300000: false.\nCompared main.suff_intra_par_13 <= 400: true.\nCompared main.suff_outer_par_14 <= 300000: true.\nCompared main.suff_intra_par_15 <= 1200: true.\nruntime: 70684\n\nCompared main.suff_outer_par_0 <= 300000: false.\nCompared main.suff_outer_par_1 <= 2400000: false.\nCompared main.suff_outer_par_2 <= 19200000: true.\nCompared main.suff_intra_par_3 <= 128: true.\nCompared main.suff_intra_par_4 <= 128: true.\nCompared main.suff_outer_par_5 <= 300000: true.\nCompared main.suff_outer_par_6 <= 2400000: true.\nCompared main.suff_outer_par_7 <= 300000: true.\nCompared main.suff_outer_par_8 <= 2400000: false.\nCompared main.suff_outer_par_9 <= 300000: false.\nCompared main.suff_outer_par_10 <= 480000000: true.\nCompared main.suff_intra_par_11 <= 1600: true.\nCompared main.suff_outer_par_12 <= 300000: false.\nCompared main.suff_intra_par_13 <= 400: true.\nCompared main.suff_outer_par_14 <= 300000: true.\nCompared main.suff_intra_par_15 <= 1200: true.\nruntime: 70706\n\nCompared main.suff_outer_par_0 <= 300000: false.\nCompared main.suff_outer_par_1 <= 2400000: false.\nCompared main.suff_outer_par_2 <= 19200000: true.\nCompared main.suff_intra_par_3 <= 128: true.\nCompared main.suff_intra_par_4 <= 128: true.\nCompared main.suff_outer_par_5 <= 300000: true.\nCompared main.suff_outer_par_6 <= 2400000: true.\nCompared main.suff_outer_par_7 <= 300000: true.\nCompared main.suff_outer_par_8 <= 2400000: false.\nCompared main.suff_outer_par_9 <= 300000: false.\nCompared main.suff_outer_par_10 <= 480000000: true.\nCompared main.suff_intra_par_11 <= 1600: true.\nCompared main.suff_outer_par_12 <= 300000: false.\nCompared main.suff_intra_par_13 <= 400: true.\nCompared main.suff_outer_par_14 <= 300000: true.\nCompared main.suff_intra_par_15 <= 1200: true.\nruntime: 70652\n\nCompared main.suff_outer_par_0 <= 300000: false.\nCompared main.suff_outer_par_1 <= 2400000: false.\nCompared main.suff_outer_par_2 <= 19200000: true.\nCompared main.suff_intra_par_3 <= 128: true.\nCompared main.suff_intra_par_4 <= 128: true.\nCompared main.suff_outer_par_5 <= 300000: true.\nCompared main.suff_outer_par_6 <= 2400000: true.\nCompared main.suff_outer_par_7 <= 300000: true.\nCompared main.suff_outer_par_8 <= 2400000: false.\nCompared main.suff_outer_par_9 <= 300000: false.\nCompared main.suff_outer_par_10 <= 480000000: true.\nCompared main.suff_intra_par_11 <= 1600: true.\nCompared main.suff_outer_par_12 <= 300000: false.\nCompared main.suff_intra_par_13 <= 400: true.\nCompared main.suff_outer_par_14 <= 300000: true.\nCompared main.suff_intra_par_15 <= 1200: true.\nruntime: 70688\n\nCompared main.suff_outer_par_0 <= 300000: false.\nCompared main.suff_outer_par_1 <= 2400000: false.\nCompared main.suff_outer_par_2 <= 19200000: true.\nCompared main.suff_intra_par_3 <= 128: true.\nCompared main.suff_intra_par_4 <= 128: true.\nCompared main.suff_outer_par_5 <= 300000: true.\nCompared main.suff_outer_par_6 <= 2400000: true.\nCompared main.suff_outer_par_7 <= 300000: true.\nCompared main.suff_outer_par_8 <= 2400000: false.\nCompared main.suff_outer_par_9 <= 300000: false.\nCompared main.suff_outer_par_10 <= 480000000: true.\nCompared main.suff_intra_par_11 <= 1600: true.\nCompared main.suff_outer_par_12 <= 300000: false.\nCompared main.suff_intra_par_13 <= 400: true.\nCompared main.suff_outer_par_14 <= 300000: true.\nCompared main.suff_intra_par_15 <= 1200: true.\nruntime: 70665\n\nCompared main.suff_outer_par_0 <= 300000: false.\nCompared main.suff_outer_par_1 <= 2400000: false.\nCompared main.suff_outer_par_2 <= 19200000: true.\nCompared main.suff_intra_par_3 <= 128: true.\nCompared main.suff_intra_par_4 <= 128: true.\nCompared main.suff_outer_par_5 <= 300000: true.\nCompared main.suff_outer_par_6 <= 2400000: true.\nCompared main.suff_outer_par_7 <= 300000: true.\nCompared main.suff_outer_par_8 <= 2400000: false.\nCompared main.suff_outer_par_9 <= 300000: false.\nCompared main.suff_outer_par_10 <= 480000000: true.\nCompared main.suff_intra_par_11 <= 1600: true.\nCompared main.suff_outer_par_12 <= 300000: false.\nCompared main.suff_intra_par_13 <= 400: true.\nCompared main.suff_outer_par_14 <= 300000: true.\nCompared main.suff_intra_par_15 <= 1200: true.\nruntime: 70627\n\nCompared main.suff_outer_par_0 <= 300000: false.\nCompared main.suff_outer_par_1 <= 2400000: false.\nCompared main.suff_outer_par_2 <= 19200000: true.\nCompared main.suff_intra_par_3 <= 128: true.\nCompared main.suff_intra_par_4 <= 128: true.\nCompared main.suff_outer_par_5 <= 300000: true.\nCompared main.suff_outer_par_6 <= 2400000: true.\nCompared main.suff_outer_par_7 <= 300000: true.\nCompared main.suff_outer_par_8 <= 2400000: false.\nCompared main.suff_outer_par_9 <= 300000: false.\nCompared main.suff_outer_par_10 <= 480000000: true.\nCompared main.suff_intra_par_11 <= 1600: true.\nCompared main.suff_outer_par_12 <= 300000: false.\nCompared main.suff_intra_par_13 <= 400: true.\nCompared main.suff_outer_par_14 <= 300000: true.\nCompared main.suff_intra_par_15 <= 1200: true.\nruntime: 70677\n\nCompared main.suff_outer_par_0 <= 300000: false.\nCompared main.suff_outer_par_1 <= 2400000: false.\nCompared main.suff_outer_par_2 <= 19200000: true.\nCompared main.suff_intra_par_3 <= 128: true.\nCompared main.suff_intra_par_4 <= 128: true.\nCompared main.suff_outer_par_5 <= 300000: true.\nCompared main.suff_outer_par_6 <= 2400000: true.\nCompared main.suff_outer_par_7 <= 300000: true.\nCompared main.suff_outer_par_8 <= 2400000: false.\nCompared main.suff_outer_par_9 <= 300000: false.\nCompared main.suff_outer_par_10 <= 480000000: true.\nCompared main.suff_intra_par_11 <= 1600: true.\nCompared main.suff_outer_par_12 <= 300000: false.\nCompared main.suff_intra_par_13 <= 400: true.\nCompared main.suff_outer_par_14 <= 300000: true.\nCompared main.suff_intra_par_15 <= 1200: true.\nruntime: 70690\n\nCompared main.suff_outer_par_0 <= 300000: false.\nCompared main.suff_outer_par_1 <= 2400000: false.\nCompared main.suff_outer_par_2 <= 19200000: true.\nCompared main.suff_intra_par_3 <= 128: true.\nCompared main.suff_intra_par_4 <= 128: true.\nCompared main.suff_outer_par_5 <= 300000: true.\nCompared main.suff_outer_par_6 <= 2400000: true.\nCompared main.suff_outer_par_7 <= 300000: true.\nCompared main.suff_outer_par_8 <= 2400000: false.\nCompared main.suff_outer_par_9 <= 300000: false.\nCompared main.suff_outer_par_10 <= 480000000: true.\nCompared main.suff_intra_par_11 <= 1600: true.\nCompared main.suff_outer_par_12 <= 300000: false.\nCompared main.suff_intra_par_13 <= 400: true.\nCompared main.suff_outer_par_14 <= 300000: true.\nCompared main.suff_intra_par_15 <= 1200: true.\nruntime: 70703\n\nCompared main.suff_outer_par_0 <= 300000: false.\nCompared main.suff_outer_par_1 <= 2400000: false.\nCompared main.suff_outer_par_2 <= 19200000: true.\nCompared main.suff_intra_par_3 <= 128: true.\nCompared main.suff_intra_par_4 <= 128: true.\nCompared main.suff_outer_par_5 <= 300000: true.\nCompared main.suff_outer_par_6 <= 2400000: true.\nCompared main.suff_outer_par_7 <= 300000: true.\nCompared main.suff_outer_par_8 <= 2400000: false.\nCompared main.suff_outer_par_9 <= 300000: false.\nCompared main.suff_outer_par_10 <= 480000000: true.\nCompared main.suff_intra_par_11 <= 1600: true.\nCompared main.suff_outer_par_12 <= 300000: false.\nCompared main.suff_intra_par_13 <= 400: true.\nCompared main.suff_outer_par_14 <= 300000: true.\nCompared main.suff_intra_par_15 <= 1200: true.\nruntime: 70696\n\nCompared main.suff_outer_par_0 <= 300000: false.\nCompared main.suff_outer_par_1 <= 2400000: false.\nCompared main.suff_outer_par_2 <= 19200000: true.\nCompared main.suff_intra_par_3 <= 128: true.\nCompared main.suff_intra_par_4 <= 128: true.\nCompared main.suff_outer_par_5 <= 300000: true.\nCompared main.suff_outer_par_6 <= 2400000: true.\nCompared main.suff_outer_par_7 <= 300000: true.\nCompared main.suff_outer_par_8 <= 2400000: false.\nCompared main.suff_outer_par_9 <= 300000: false.\nCompared main.suff_outer_par_10 <= 480000000: true.\nCompared main.suff_intra_par_11 <= 1600: true.\nCompared main.suff_outer_par_12 <= 300000: false.\nCompared main.suff_intra_par_13 <= 400: true.\nCompared main.suff_outer_par_14 <= 300000: true.\nCompared main.suff_intra_par_15 <= 1200: true.\nruntime: 70732\n\nCompared main.suff_outer_par_0 <= 300000: false.\nCompared main.suff_outer_par_1 <= 2400000: false.\nCompared main.suff_outer_par_2 <= 19200000: true.\nCompared main.suff_intra_par_3 <= 128: true.\nCompared main.suff_intra_par_4 <= 128: true.\nCompared main.suff_outer_par_5 <= 300000: true.\nCompared main.suff_outer_par_6 <= 2400000: true.\nCompared main.suff_outer_par_7 <= 300000: true.\nCompared main.suff_outer_par_8 <= 2400000: false.\nCompared main.suff_outer_par_9 <= 300000: false.\nCompared main.suff_outer_par_10 <= 480000000: true.\nCompared main.suff_intra_par_11 <= 1600: true.\nCompared main.suff_outer_par_12 <= 300000: false.\nCompared main.suff_intra_par_13 <= 400: true.\nCompared main.suff_outer_par_14 <= 300000: true.\nCompared main.suff_intra_par_15 <= 1200: true.\nruntime: 70682\n\nCompared main.suff_outer_par_0 <= 300000: false.\nCompared main.suff_outer_par_1 <= 2400000: false.\nCompared main.suff_outer_par_2 <= 19200000: true.\nCompared main.suff_intra_par_3 <= 128: true.\nCompared main.suff_intra_par_4 <= 128: true.\nCompared main.suff_outer_par_5 <= 300000: true.\nCompared main.suff_outer_par_6 <= 2400000: true.\nCompared main.suff_outer_par_7 <= 300000: true.\nCompared main.suff_outer_par_8 <= 2400000: false.\nCompared main.suff_outer_par_9 <= 300000: false.\nCompared main.suff_outer_par_10 <= 480000000: true.\nCompared main.suff_intra_par_11 <= 1600: true.\nCompared main.suff_outer_par_12 <= 300000: false.\nCompared main.suff_intra_par_13 <= 400: true.\nCompared main.suff_outer_par_14 <= 300000: true.\nCompared main.suff_intra_par_15 <= 1200: true.\nruntime: 70729\n\nCompared main.suff_outer_par_0 <= 300000: false.\nCompared main.suff_outer_par_1 <= 2400000: false.\nCompared main.suff_outer_par_2 <= 19200000: true.\nCompared main.suff_intra_par_3 <= 128: true.\nCompared main.suff_intra_par_4 <= 128: true.\nCompared main.suff_outer_par_5 <= 300000: true.\nCompared main.suff_outer_par_6 <= 2400000: true.\nCompared main.suff_outer_par_7 <= 300000: true.\nCompared main.suff_outer_par_8 <= 2400000: false.\nCompared main.suff_outer_par_9 <= 300000: false.\nCompared main.suff_outer_par_10 <= 480000000: true.\nCompared main.suff_intra_par_11 <= 1600: true.\nCompared main.suff_outer_par_12 <= 300000: false.\nCompared main.suff_intra_par_13 <= 400: true.\nCompared main.suff_outer_par_14 <= 300000: true.\nCompared main.suff_intra_par_15 <= 1200: true.\nruntime: 70719\n\nCompared main.suff_outer_par_0 <= 300000: false.\nCompared main.suff_outer_par_1 <= 2400000: false.\nCompared main.suff_outer_par_2 <= 19200000: true.\nCompared main.suff_intra_par_3 <= 128: true.\nCompared main.suff_intra_par_4 <= 128: true.\nCompared main.suff_outer_par_5 <= 300000: true.\nCompared main.suff_outer_par_6 <= 2400000: true.\nCompared main.suff_outer_par_7 <= 300000: true.\nCompared main.suff_outer_par_8 <= 2400000: false.\nCompared main.suff_outer_par_9 <= 300000: false.\nCompared main.suff_outer_par_10 <= 480000000: true.\nCompared main.suff_intra_par_11 <= 1600: true.\nCompared main.suff_outer_par_12 <= 300000: false.\nCompared main.suff_intra_par_13 <= 400: true.\nCompared main.suff_outer_par_14 <= 300000: true.\nCompared main.suff_intra_par_15 <= 1200: true.\nruntime: 70720\n\nCompared main.suff_outer_par_0 <= 300000: false.\nCompared main.suff_outer_par_1 <= 2400000: false.\nCompared main.suff_outer_par_2 <= 19200000: true.\nCompared main.suff_intra_par_3 <= 128: true.\nCompared main.suff_intra_par_4 <= 128: true.\nCompared main.suff_outer_par_5 <= 300000: true.\nCompared main.suff_outer_par_6 <= 2400000: true.\nCompared main.suff_outer_par_7 <= 300000: true.\nCompared main.suff_outer_par_8 <= 2400000: false.\nCompared main.suff_outer_par_9 <= 300000: false.\nCompared main.suff_outer_par_10 <= 480000000: true.\nCompared main.suff_intra_par_11 <= 1600: true.\nCompared main.suff_outer_par_12 <= 300000: false.\nCompared main.suff_intra_par_13 <= 400: true.\nCompared main.suff_outer_par_14 <= 300000: true.\nCompared main.suff_intra_par_15 <= 1200: true.\nruntime: 70697\n\nCompared main.suff_outer_par_0 <= 300000: false.\nCompared main.suff_outer_par_1 <= 2400000: false.\nCompared main.suff_outer_par_2 <= 19200000: true.\nCompared main.suff_intra_par_3 <= 128: true.\nCompared main.suff_intra_par_4 <= 128: true.\nCompared main.suff_outer_par_5 <= 300000: true.\nCompared main.suff_outer_par_6 <= 2400000: true.\nCompared main.suff_outer_par_7 <= 300000: true.\nCompared main.suff_outer_par_8 <= 2400000: false.\nCompared main.suff_outer_par_9 <= 300000: false.\nCompared main.suff_outer_par_10 <= 480000000: true.\nCompared main.suff_intra_par_11 <= 1600: true.\nCompared main.suff_outer_par_12 <= 300000: false.\nCompared main.suff_intra_par_13 <= 400: true.\nCompared main.suff_outer_par_14 <= 300000: true.\nCompared main.suff_intra_par_15 <= 1200: true.\nruntime: 70761\n\nCompared main.suff_outer_par_0 <= 300000: false.\nCompared main.suff_outer_par_1 <= 2400000: false.\nCompared main.suff_outer_par_2 <= 19200000: true.\nCompared main.suff_intra_par_3 <= 128: true.\nCompared main.suff_intra_par_4 <= 128: true.\nCompared main.suff_outer_par_5 <= 300000: true.\nCompared main.suff_outer_par_6 <= 2400000: true.\nCompared main.suff_outer_par_7 <= 300000: true.\nCompared main.suff_outer_par_8 <= 2400000: false.\nCompared main.suff_outer_par_9 <= 300000: false.\nCompared main.suff_outer_par_10 <= 480000000: true.\nCompared main.suff_intra_par_11 <= 1600: true.\nCompared main.suff_outer_par_12 <= 300000: false.\nCompared main.suff_intra_par_13 <= 400: true.\nCompared main.suff_outer_par_14 <= 300000: true.\nCompared main.suff_intra_par_15 <= 1200: true.\nruntime: 70691\n\nCompared main.suff_outer_par_0 <= 300000: false.\nCompared main.suff_outer_par_1 <= 2400000: false.\nCompared main.suff_outer_par_2 <= 19200000: true.\nCompared main.suff_intra_par_3 <= 128: true.\nCompared main.suff_intra_par_4 <= 128: true.\nCompared main.suff_outer_par_5 <= 300000: true.\nCompared main.suff_outer_par_6 <= 2400000: true.\nCompared main.suff_outer_par_7 <= 300000: true.\nCompared main.suff_outer_par_8 <= 2400000: false.\nCompared main.suff_outer_par_9 <= 300000: false.\nCompared main.suff_outer_par_10 <= 480000000: true.\nCompared main.suff_intra_par_11 <= 1600: true.\nCompared main.suff_outer_par_12 <= 300000: false.\nCompared main.suff_intra_par_13 <= 400: true.\nCompared main.suff_outer_par_14 <= 300000: true.\nCompared main.suff_intra_par_15 <= 1200: true.\nruntime: 70701\n\nCompared main.suff_outer_par_0 <= 300000: false.\nCompared main.suff_outer_par_1 <= 2400000: false.\nCompared main.suff_outer_par_2 <= 19200000: true.\nCompared main.suff_intra_par_3 <= 128: true.\nCompared main.suff_intra_par_4 <= 128: true.\nCompared main.suff_outer_par_5 <= 300000: true.\nCompared main.suff_outer_par_6 <= 2400000: true.\nCompared main.suff_outer_par_7 <= 300000: true.\nCompared main.suff_outer_par_8 <= 2400000: false.\nCompared main.suff_outer_par_9 <= 300000: false.\nCompared main.suff_outer_par_10 <= 480000000: true.\nCompared main.suff_intra_par_11 <= 1600: true.\nCompared main.suff_outer_par_12 <= 300000: false.\nCompared main.suff_intra_par_13 <= 400: true.\nCompared main.suff_outer_par_14 <= 300000: true.\nCompared main.suff_intra_par_15 <= 1200: true.\nruntime: 70643\n\nCompared main.suff_outer_par_0 <= 300000: false.\nCompared main.suff_outer_par_1 <= 2400000: false.\nCompared main.suff_outer_par_2 <= 19200000: true.\nCompared main.suff_intra_par_3 <= 128: true.\nCompared main.suff_intra_par_4 <= 128: true.\nCompared main.suff_outer_par_5 <= 300000: true.\nCompared main.suff_outer_par_6 <= 2400000: true.\nCompared main.suff_outer_par_7 <= 300000: true.\nCompared main.suff_outer_par_8 <= 2400000: false.\nCompared main.suff_outer_par_9 <= 300000: false.\nCompared main.suff_outer_par_10 <= 480000000: true.\nCompared main.suff_intra_par_11 <= 1600: true.\nCompared main.suff_outer_par_12 <= 300000: false.\nCompared main.suff_intra_par_13 <= 400: true.\nCompared main.suff_outer_par_14 <= 300000: true.\nCompared main.suff_intra_par_15 <= 1200: true.\nruntime: 70714\n\nCompared main.suff_outer_par_0 <= 300000: false.\nCompared main.suff_outer_par_1 <= 2400000: false.\nCompared main.suff_outer_par_2 <= 19200000: true.\nCompared main.suff_intra_par_3 <= 128: true.\nCompared main.suff_intra_par_4 <= 128: true.\nCompared main.suff_outer_par_5 <= 300000: true.\nCompared main.suff_outer_par_6 <= 2400000: true.\nCompared main.suff_outer_par_7 <= 300000: true.\nCompared main.suff_outer_par_8 <= 2400000: false.\nCompared main.suff_outer_par_9 <= 300000: false.\nCompared main.suff_outer_par_10 <= 480000000: true.\nCompared main.suff_intra_par_11 <= 1600: true.\nCompared main.suff_outer_par_12 <= 300000: false.\nCompared main.suff_intra_par_13 <= 400: true.\nCompared main.suff_outer_par_14 <= 300000: true.\nCompared main.suff_intra_par_15 <= 1200: true.\nruntime: 70654\n\nCompared main.suff_outer_par_0 <= 300000: false.\nCompared main.suff_outer_par_1 <= 2400000: false.\nCompared main.suff_outer_par_2 <= 19200000: true.\nCompared main.suff_intra_par_3 <= 128: true.\nCompared main.suff_intra_par_4 <= 128: true.\nCompared main.suff_outer_par_5 <= 300000: true.\nCompared main.suff_outer_par_6 <= 2400000: true.\nCompared main.suff_outer_par_7 <= 300000: true.\nCompared main.suff_outer_par_8 <= 2400000: false.\nCompared main.suff_outer_par_9 <= 300000: false.\nCompared main.suff_outer_par_10 <= 480000000: true.\nCompared main.suff_intra_par_11 <= 1600: true.\nCompared main.suff_outer_par_12 <= 300000: false.\nCompared main.suff_intra_par_13 <= 400: true.\nCompared main.suff_outer_par_14 <= 300000: true.\nCompared main.suff_intra_par_15 <= 1200: true.\nruntime: 70699\n\nCompared main.suff_outer_par_0 <= 300000: false.\nCompared main.suff_outer_par_1 <= 2400000: false.\nCompared main.suff_outer_par_2 <= 19200000: true.\nCompared main.suff_intra_par_3 <= 128: true.\nCompared main.suff_intra_par_4 <= 128: true.\nCompared main.suff_outer_par_5 <= 300000: true.\nCompared main.suff_outer_par_6 <= 2400000: true.\nCompared main.suff_outer_par_7 <= 300000: true.\nCompared main.suff_outer_par_8 <= 2400000: false.\nCompared main.suff_outer_par_9 <= 300000: false.\nCompared main.suff_outer_par_10 <= 480000000: true.\nCompared main.suff_intra_par_11 <= 1600: true.\nCompared main.suff_outer_par_12 <= 300000: false.\nCompared main.suff_intra_par_13 <= 400: true.\nCompared main.suff_outer_par_14 <= 300000: true.\nCompared main.suff_intra_par_15 <= 1200: true.\nruntime: 70626\n\nCompared main.suff_outer_par_0 <= 300000: false.\nCompared main.suff_outer_par_1 <= 2400000: false.\nCompared main.suff_outer_par_2 <= 19200000: true.\nCompared main.suff_intra_par_3 <= 128: true.\nCompared main.suff_intra_par_4 <= 128: true.\nCompared main.suff_outer_par_5 <= 300000: true.\nCompared main.suff_outer_par_6 <= 2400000: true.\nCompared main.suff_outer_par_7 <= 300000: true.\nCompared main.suff_outer_par_8 <= 2400000: false.\nCompared main.suff_outer_par_9 <= 300000: false.\nCompared main.suff_outer_par_10 <= 480000000: true.\nCompared main.suff_intra_par_11 <= 1600: true.\nCompared main.suff_outer_par_12 <= 300000: false.\nCompared main.suff_intra_par_13 <= 400: true.\nCompared main.suff_outer_par_14 <= 300000: true.\nCompared main.suff_intra_par_15 <= 1200: true.\nruntime: 70661\n\nCompared main.suff_outer_par_0 <= 300000: false.\nCompared main.suff_outer_par_1 <= 2400000: false.\nCompared main.suff_outer_par_2 <= 19200000: true.\nCompared main.suff_intra_par_3 <= 128: true.\nCompared main.suff_intra_par_4 <= 128: true.\nCompared main.suff_outer_par_5 <= 300000: true.\nCompared main.suff_outer_par_6 <= 2400000: true.\nCompared main.suff_outer_par_7 <= 300000: true.\nCompared main.suff_outer_par_8 <= 2400000: false.\nCompared main.suff_outer_par_9 <= 300000: false.\nCompared main.suff_outer_par_10 <= 480000000: true.\nCompared main.suff_intra_par_11 <= 1600: true.\nCompared main.suff_outer_par_12 <= 300000: false.\nCompared main.suff_intra_par_13 <= 400: true.\nCompared main.suff_outer_par_14 <= 300000: true.\nCompared main.suff_intra_par_15 <= 1200: true.\nruntime: 70679\n\nCompared main.suff_outer_par_0 <= 300000: false.\nCompared main.suff_outer_par_1 <= 2400000: false.\nCompared main.suff_outer_par_2 <= 19200000: true.\nCompared main.suff_intra_par_3 <= 128: true.\nCompared main.suff_intra_par_4 <= 128: true.\nCompared main.suff_outer_par_5 <= 300000: true.\nCompared main.suff_outer_par_6 <= 2400000: true.\nCompared main.suff_outer_par_7 <= 300000: true.\nCompared main.suff_outer_par_8 <= 2400000: false.\nCompared main.suff_outer_par_9 <= 300000: false.\nCompared main.suff_outer_par_10 <= 480000000: true.\nCompared main.suff_intra_par_11 <= 1600: true.\nCompared main.suff_outer_par_12 <= 300000: false.\nCompared main.suff_intra_par_13 <= 400: true.\nCompared main.suff_outer_par_14 <= 300000: true.\nCompared main.suff_intra_par_15 <= 1200: true.\nruntime: 70687\n\nCompared main.suff_outer_par_0 <= 300000: false.\nCompared main.suff_outer_par_1 <= 2400000: false.\nCompared main.suff_outer_par_2 <= 19200000: true.\nCompared main.suff_intra_par_3 <= 128: true.\nCompared main.suff_intra_par_4 <= 128: true.\nCompared main.suff_outer_par_5 <= 300000: true.\nCompared main.suff_outer_par_6 <= 2400000: true.\nCompared main.suff_outer_par_7 <= 300000: true.\nCompared main.suff_outer_par_8 <= 2400000: false.\nCompared main.suff_outer_par_9 <= 300000: false.\nCompared main.suff_outer_par_10 <= 480000000: true.\nCompared main.suff_intra_par_11 <= 1600: true.\nCompared main.suff_outer_par_12 <= 300000: false.\nCompared main.suff_intra_par_13 <= 400: true.\nCompared main.suff_outer_par_14 <= 300000: true.\nCompared main.suff_intra_par_15 <= 1200: true.\nruntime: 70687\n\nCompared main.suff_outer_par_0 <= 300000: false.\nCompared main.suff_outer_par_1 <= 2400000: false.\nCompared main.suff_outer_par_2 <= 19200000: true.\nCompared main.suff_intra_par_3 <= 128: true.\nCompared main.suff_intra_par_4 <= 128: true.\nCompared main.suff_outer_par_5 <= 300000: true.\nCompared main.suff_outer_par_6 <= 2400000: true.\nCompared main.suff_outer_par_7 <= 300000: true.\nCompared main.suff_outer_par_8 <= 2400000: false.\nCompared main.suff_outer_par_9 <= 300000: false.\nCompared main.suff_outer_par_10 <= 480000000: true.\nCompared main.suff_intra_par_11 <= 1600: true.\nCompared main.suff_outer_par_12 <= 300000: false.\nCompared main.suff_intra_par_13 <= 400: true.\nCompared main.suff_outer_par_14 <= 300000: true.\nCompared main.suff_intra_par_15 <= 1200: true.\nruntime: 70606\n\nCompared main.suff_outer_par_0 <= 300000: false.\nCompared main.suff_outer_par_1 <= 2400000: false.\nCompared main.suff_outer_par_2 <= 19200000: true.\nCompared main.suff_intra_par_3 <= 128: true.\nCompared main.suff_intra_par_4 <= 128: true.\nCompared main.suff_outer_par_5 <= 300000: true.\nCompared main.suff_outer_par_6 <= 2400000: true.\nCompared main.suff_outer_par_7 <= 300000: true.\nCompared main.suff_outer_par_8 <= 2400000: false.\nCompared main.suff_outer_par_9 <= 300000: false.\nCompared main.suff_outer_par_10 <= 480000000: true.\nCompared main.suff_intra_par_11 <= 1600: true.\nCompared main.suff_outer_par_12 <= 300000: false.\nCompared main.suff_intra_par_13 <= 400: true.\nCompared main.suff_outer_par_14 <= 300000: true.\nCompared main.suff_intra_par_15 <= 1200: true.\nruntime: 70591\n\nCompared main.suff_outer_par_0 <= 300000: false.\nCompared main.suff_outer_par_1 <= 2400000: false.\nCompared main.suff_outer_par_2 <= 19200000: true.\nCompared main.suff_intra_par_3 <= 128: true.\nCompared main.suff_intra_par_4 <= 128: true.\nCompared main.suff_outer_par_5 <= 300000: true.\nCompared main.suff_outer_par_6 <= 2400000: true.\nCompared main.suff_outer_par_7 <= 300000: true.\nCompared main.suff_outer_par_8 <= 2400000: false.\nCompared main.suff_outer_par_9 <= 300000: false.\nCompared main.suff_outer_par_10 <= 480000000: true.\nCompared main.suff_intra_par_11 <= 1600: true.\nCompared main.suff_outer_par_12 <= 300000: false.\nCompared main.suff_intra_par_13 <= 400: true.\nCompared main.suff_outer_par_14 <= 300000: true.\nCompared main.suff_intra_par_15 <= 1200: true.\nruntime: 70615\n\nCompared main.suff_outer_par_0 <= 300000: false.\nCompared main.suff_outer_par_1 <= 2400000: false.\nCompared main.suff_outer_par_2 <= 19200000: true.\nCompared main.suff_intra_par_3 <= 128: true.\nCompared main.suff_intra_par_4 <= 128: true.\nCompared main.suff_outer_par_5 <= 300000: true.\nCompared main.suff_outer_par_6 <= 2400000: true.\nCompared main.suff_outer_par_7 <= 300000: true.\nCompared main.suff_outer_par_8 <= 2400000: false.\nCompared main.suff_outer_par_9 <= 300000: false.\nCompared main.suff_outer_par_10 <= 480000000: true.\nCompared main.suff_intra_par_11 <= 1600: true.\nCompared main.suff_outer_par_12 <= 300000: false.\nCompared main.suff_intra_par_13 <= 400: true.\nCompared main.suff_outer_par_14 <= 300000: true.\nCompared main.suff_intra_par_15 <= 1200: true.\nruntime: 70642\n\nCompared main.suff_outer_par_0 <= 300000: false.\nCompared main.suff_outer_par_1 <= 2400000: false.\nCompared main.suff_outer_par_2 <= 19200000: true.\nCompared main.suff_intra_par_3 <= 128: true.\nCompared main.suff_intra_par_4 <= 128: true.\nCompared main.suff_outer_par_5 <= 300000: true.\nCompared main.suff_outer_par_6 <= 2400000: true.\nCompared main.suff_outer_par_7 <= 300000: true.\nCompared main.suff_outer_par_8 <= 2400000: false.\nCompared main.suff_outer_par_9 <= 300000: false.\nCompared main.suff_outer_par_10 <= 480000000: true.\nCompared main.suff_intra_par_11 <= 1600: true.\nCompared main.suff_outer_par_12 <= 300000: false.\nCompared main.suff_intra_par_13 <= 400: true.\nCompared main.suff_outer_par_14 <= 300000: true.\nCompared main.suff_intra_par_15 <= 1200: true.\nruntime: 70689\n\nCompared main.suff_outer_par_0 <= 300000: false.\nCompared main.suff_outer_par_1 <= 2400000: false.\nCompared main.suff_outer_par_2 <= 19200000: true.\nCompared main.suff_intra_par_3 <= 128: true.\nCompared main.suff_intra_par_4 <= 128: true.\nCompared main.suff_outer_par_5 <= 300000: true.\nCompared main.suff_outer_par_6 <= 2400000: true.\nCompared main.suff_outer_par_7 <= 300000: true.\nCompared main.suff_outer_par_8 <= 2400000: false.\nCompared main.suff_outer_par_9 <= 300000: false.\nCompared main.suff_outer_par_10 <= 480000000: true.\nCompared main.suff_intra_par_11 <= 1600: true.\nCompared main.suff_outer_par_12 <= 300000: false.\nCompared main.suff_intra_par_13 <= 400: true.\nCompared main.suff_outer_par_14 <= 300000: true.\nCompared main.suff_intra_par_15 <= 1200: true.\nruntime: 70672\n\nCompared main.suff_outer_par_0 <= 300000: false.\nCompared main.suff_outer_par_1 <= 2400000: false.\nCompared main.suff_outer_par_2 <= 19200000: true.\nCompared main.suff_intra_par_3 <= 128: true.\nCompared main.suff_intra_par_4 <= 128: true.\nCompared main.suff_outer_par_5 <= 300000: true.\nCompared main.suff_outer_par_6 <= 2400000: true.\nCompared main.suff_outer_par_7 <= 300000: true.\nCompared main.suff_outer_par_8 <= 2400000: false.\nCompared main.suff_outer_par_9 <= 300000: false.\nCompared main.suff_outer_par_10 <= 480000000: true.\nCompared main.suff_intra_par_11 <= 1600: true.\nCompared main.suff_outer_par_12 <= 300000: false.\nCompared main.suff_intra_par_13 <= 400: true.\nCompared main.suff_outer_par_14 <= 300000: true.\nCompared main.suff_intra_par_15 <= 1200: true.\nruntime: 70613\n\nCompared main.suff_outer_par_0 <= 300000: false.\nCompared main.suff_outer_par_1 <= 2400000: false.\nCompared main.suff_outer_par_2 <= 19200000: true.\nCompared main.suff_intra_par_3 <= 128: true.\nCompared main.suff_intra_par_4 <= 128: true.\nCompared main.suff_outer_par_5 <= 300000: true.\nCompared main.suff_outer_par_6 <= 2400000: true.\nCompared main.suff_outer_par_7 <= 300000: true.\nCompared main.suff_outer_par_8 <= 2400000: false.\nCompared main.suff_outer_par_9 <= 300000: false.\nCompared main.suff_outer_par_10 <= 480000000: true.\nCompared main.suff_intra_par_11 <= 1600: true.\nCompared main.suff_outer_par_12 <= 300000: false.\nCompared main.suff_intra_par_13 <= 400: true.\nCompared main.suff_outer_par_14 <= 300000: true.\nCompared main.suff_intra_par_15 <= 1200: true.\nruntime: 70687\n\nCompared main.suff_outer_par_0 <= 300000: false.\nCompared main.suff_outer_par_1 <= 2400000: false.\nCompared main.suff_outer_par_2 <= 19200000: true.\nCompared main.suff_intra_par_3 <= 128: true.\nCompared main.suff_intra_par_4 <= 128: true.\nCompared main.suff_outer_par_5 <= 300000: true.\nCompared main.suff_outer_par_6 <= 2400000: true.\nCompared main.suff_outer_par_7 <= 300000: true.\nCompared main.suff_outer_par_8 <= 2400000: false.\nCompared main.suff_outer_par_9 <= 300000: false.\nCompared main.suff_outer_par_10 <= 480000000: true.\nCompared main.suff_intra_par_11 <= 1600: true.\nCompared main.suff_outer_par_12 <= 300000: false.\nCompared main.suff_intra_par_13 <= 400: true.\nCompared main.suff_outer_par_14 <= 300000: true.\nCompared main.suff_intra_par_15 <= 1200: true.\nruntime: 70713\n\nCompared main.suff_outer_par_0 <= 300000: false.\nCompared main.suff_outer_par_1 <= 2400000: false.\nCompared main.suff_outer_par_2 <= 19200000: true.\nCompared main.suff_intra_par_3 <= 128: true.\nCompared main.suff_intra_par_4 <= 128: true.\nCompared main.suff_outer_par_5 <= 300000: true.\nCompared main.suff_outer_par_6 <= 2400000: true.\nCompared main.suff_outer_par_7 <= 300000: true.\nCompared main.suff_outer_par_8 <= 2400000: false.\nCompared main.suff_outer_par_9 <= 300000: false.\nCompared main.suff_outer_par_10 <= 480000000: true.\nCompared main.suff_intra_par_11 <= 1600: true.\nCompared main.suff_outer_par_12 <= 300000: false.\nCompared main.suff_intra_par_13 <= 400: true.\nCompared main.suff_outer_par_14 <= 300000: true.\nCompared main.suff_intra_par_15 <= 1200: true.\nruntime: 70683\n\nCompared main.suff_outer_par_0 <= 300000: false.\nCompared main.suff_outer_par_1 <= 2400000: false.\nCompared main.suff_outer_par_2 <= 19200000: true.\nCompared main.suff_intra_par_3 <= 128: true.\nCompared main.suff_intra_par_4 <= 128: true.\nCompared main.suff_outer_par_5 <= 300000: true.\nCompared main.suff_outer_par_6 <= 2400000: true.\nCompared main.suff_outer_par_7 <= 300000: true.\nCompared main.suff_outer_par_8 <= 2400000: false.\nCompared main.suff_outer_par_9 <= 300000: false.\nCompared main.suff_outer_par_10 <= 480000000: true.\nCompared main.suff_intra_par_11 <= 1600: true.\nCompared main.suff_outer_par_12 <= 300000: false.\nCompared main.suff_intra_par_13 <= 400: true.\nCompared main.suff_outer_par_14 <= 300000: true.\nCompared main.suff_intra_par_15 <= 1200: true.\nruntime: 70682\n\nCompared main.suff_outer_par_0 <= 300000: false.\nCompared main.suff_outer_par_1 <= 2400000: false.\nCompared main.suff_outer_par_2 <= 19200000: true.\nCompared main.suff_intra_par_3 <= 128: true.\nCompared main.suff_intra_par_4 <= 128: true.\nCompared main.suff_outer_par_5 <= 300000: true.\nCompared main.suff_outer_par_6 <= 2400000: true.\nCompared main.suff_outer_par_7 <= 300000: true.\nCompared main.suff_outer_par_8 <= 2400000: false.\nCompared main.suff_outer_par_9 <= 300000: false.\nCompared main.suff_outer_par_10 <= 480000000: true.\nCompared main.suff_intra_par_11 <= 1600: true.\nCompared main.suff_outer_par_12 <= 300000: false.\nCompared main.suff_intra_par_13 <= 400: true.\nCompared main.suff_outer_par_14 <= 300000: true.\nCompared main.suff_intra_par_15 <= 1200: true.\nruntime: 70678\n\nCompared main.suff_outer_par_0 <= 300000: false.\nCompared main.suff_outer_par_1 <= 2400000: false.\nCompared main.suff_outer_par_2 <= 19200000: true.\nCompared main.suff_intra_par_3 <= 128: true.\nCompared main.suff_intra_par_4 <= 128: true.\nCompared main.suff_outer_par_5 <= 300000: true.\nCompared main.suff_outer_par_6 <= 2400000: true.\nCompared main.suff_outer_par_7 <= 300000: true.\nCompared main.suff_outer_par_8 <= 2400000: false.\nCompared main.suff_outer_par_9 <= 300000: false.\nCompared main.suff_outer_par_10 <= 480000000: true.\nCompared main.suff_intra_par_11 <= 1600: true.\nCompared main.suff_outer_par_12 <= 300000: false.\nCompared main.suff_intra_par_13 <= 400: true.\nCompared main.suff_outer_par_14 <= 300000: true.\nCompared main.suff_intra_par_15 <= 1200: true.\nruntime: 70607\n\nCompared main.suff_outer_par_0 <= 300000: false.\nCompared main.suff_outer_par_1 <= 2400000: false.\nCompared main.suff_outer_par_2 <= 19200000: true.\nCompared main.suff_intra_par_3 <= 128: true.\nCompared main.suff_intra_par_4 <= 128: true.\nCompared main.suff_outer_par_5 <= 300000: true.\nCompared main.suff_outer_par_6 <= 2400000: true.\nCompared main.suff_outer_par_7 <= 300000: true.\nCompared main.suff_outer_par_8 <= 2400000: false.\nCompared main.suff_outer_par_9 <= 300000: false.\nCompared main.suff_outer_par_10 <= 480000000: true.\nCompared main.suff_intra_par_11 <= 1600: true.\nCompared main.suff_outer_par_12 <= 300000: false.\nCompared main.suff_intra_par_13 <= 400: true.\nCompared main.suff_outer_par_14 <= 300000: true.\nCompared main.suff_intra_par_15 <= 1200: true.\nruntime: 70683\n\nCompared main.suff_outer_par_0 <= 300000: false.\nCompared main.suff_outer_par_1 <= 2400000: false.\nCompared main.suff_outer_par_2 <= 19200000: true.\nCompared main.suff_intra_par_3 <= 128: true.\nCompared main.suff_intra_par_4 <= 128: true.\nCompared main.suff_outer_par_5 <= 300000: true.\nCompared main.suff_outer_par_6 <= 2400000: true.\nCompared main.suff_outer_par_7 <= 300000: true.\nCompared main.suff_outer_par_8 <= 2400000: false.\nCompared main.suff_outer_par_9 <= 300000: false.\nCompared main.suff_outer_par_10 <= 480000000: true.\nCompared main.suff_intra_par_11 <= 1600: true.\nCompared main.suff_outer_par_12 <= 300000: false.\nCompared main.suff_intra_par_13 <= 400: true.\nCompared main.suff_outer_par_14 <= 300000: true.\nCompared main.suff_intra_par_15 <= 1200: true.\nruntime: 70612\n\nCompared main.suff_outer_par_0 <= 300000: false.\nCompared main.suff_outer_par_1 <= 2400000: false.\nCompared main.suff_outer_par_2 <= 19200000: true.\nCompared main.suff_intra_par_3 <= 128: true.\nCompared main.suff_intra_par_4 <= 128: true.\nCompared main.suff_outer_par_5 <= 300000: true.\nCompared main.suff_outer_par_6 <= 2400000: true.\nCompared main.suff_outer_par_7 <= 300000: true.\nCompared main.suff_outer_par_8 <= 2400000: false.\nCompared main.suff_outer_par_9 <= 300000: false.\nCompared main.suff_outer_par_10 <= 480000000: true.\nCompared main.suff_intra_par_11 <= 1600: true.\nCompared main.suff_outer_par_12 <= 300000: false.\nCompared main.suff_intra_par_13 <= 400: true.\nCompared main.suff_outer_par_14 <= 300000: true.\nCompared main.suff_intra_par_15 <= 1200: true.\nruntime: 70652\n\nCompared main.suff_outer_par_0 <= 300000: false.\nCompared main.suff_outer_par_1 <= 2400000: false.\nCompared main.suff_outer_par_2 <= 19200000: true.\nCompared main.suff_intra_par_3 <= 128: true.\nCompared main.suff_intra_par_4 <= 128: true.\nCompared main.suff_outer_par_5 <= 300000: true.\nCompared main.suff_outer_par_6 <= 2400000: true.\nCompared main.suff_outer_par_7 <= 300000: true.\nCompared main.suff_outer_par_8 <= 2400000: false.\nCompared main.suff_outer_par_9 <= 300000: false.\nCompared main.suff_outer_par_10 <= 480000000: true.\nCompared main.suff_intra_par_11 <= 1600: true.\nCompared main.suff_outer_par_12 <= 300000: false.\nCompared main.suff_intra_par_13 <= 400: true.\nCompared main.suff_outer_par_14 <= 300000: true.\nCompared main.suff_intra_par_15 <= 1200: true.\nruntime: 70682\n\nCompared main.suff_outer_par_0 <= 300000: false.\nCompared main.suff_outer_par_1 <= 2400000: false.\nCompared main.suff_outer_par_2 <= 19200000: true.\nCompared main.suff_intra_par_3 <= 128: true.\nCompared main.suff_intra_par_4 <= 128: true.\nCompared main.suff_outer_par_5 <= 300000: true.\nCompared main.suff_outer_par_6 <= 2400000: true.\nCompared main.suff_outer_par_7 <= 300000: true.\nCompared main.suff_outer_par_8 <= 2400000: false.\nCompared main.suff_outer_par_9 <= 300000: false.\nCompared main.suff_outer_par_10 <= 480000000: true.\nCompared main.suff_intra_par_11 <= 1600: true.\nCompared main.suff_outer_par_12 <= 300000: false.\nCompared main.suff_intra_par_13 <= 400: true.\nCompared main.suff_outer_par_14 <= 300000: true.\nCompared main.suff_intra_par_15 <= 1200: true.\nruntime: 70652\n\nCompared main.suff_outer_par_0 <= 300000: false.\nCompared main.suff_outer_par_1 <= 2400000: false.\nCompared main.suff_outer_par_2 <= 19200000: true.\nCompared main.suff_intra_par_3 <= 128: true.\nCompared main.suff_intra_par_4 <= 128: true.\nCompared main.suff_outer_par_5 <= 300000: true.\nCompared main.suff_outer_par_6 <= 2400000: true.\nCompared main.suff_outer_par_7 <= 300000: true.\nCompared main.suff_outer_par_8 <= 2400000: false.\nCompared main.suff_outer_par_9 <= 300000: false.\nCompared main.suff_outer_par_10 <= 480000000: true.\nCompared main.suff_intra_par_11 <= 1600: true.\nCompared main.suff_outer_par_12 <= 300000: false.\nCompared main.suff_intra_par_13 <= 400: true.\nCompared main.suff_outer_par_14 <= 300000: true.\nCompared main.suff_intra_par_15 <= 1200: true.\nruntime: 70683\n\nCompared main.suff_outer_par_0 <= 300000: false.\nCompared main.suff_outer_par_1 <= 2400000: false.\nCompared main.suff_outer_par_2 <= 19200000: true.\nCompared main.suff_intra_par_3 <= 128: true.\nCompared main.suff_intra_par_4 <= 128: true.\nCompared main.suff_outer_par_5 <= 300000: true.\nCompared main.suff_outer_par_6 <= 2400000: true.\nCompared main.suff_outer_par_7 <= 300000: true.\nCompared main.suff_outer_par_8 <= 2400000: false.\nCompared main.suff_outer_par_9 <= 300000: false.\nCompared main.suff_outer_par_10 <= 480000000: true.\nCompared main.suff_intra_par_11 <= 1600: true.\nCompared main.suff_outer_par_12 <= 300000: false.\nCompared main.suff_intra_par_13 <= 400: true.\nCompared main.suff_outer_par_14 <= 300000: true.\nCompared main.suff_intra_par_15 <= 1200: true.\nruntime: 70689\n\nCompared main.suff_outer_par_0 <= 300000: false.\nCompared main.suff_outer_par_1 <= 2400000: false.\nCompared main.suff_outer_par_2 <= 19200000: true.\nCompared main.suff_intra_par_3 <= 128: true.\nCompared main.suff_intra_par_4 <= 128: true.\nCompared main.suff_outer_par_5 <= 300000: true.\nCompared main.suff_outer_par_6 <= 2400000: true.\nCompared main.suff_outer_par_7 <= 300000: true.\nCompared main.suff_outer_par_8 <= 2400000: false.\nCompared main.suff_outer_par_9 <= 300000: false.\nCompared main.suff_outer_par_10 <= 480000000: true.\nCompared main.suff_intra_par_11 <= 1600: true.\nCompared main.suff_outer_par_12 <= 300000: false.\nCompared main.suff_intra_par_13 <= 400: true.\nCompared main.suff_outer_par_14 <= 300000: true.\nCompared main.suff_intra_par_15 <= 1200: true.\nruntime: 70693\n\nCompared main.suff_outer_par_0 <= 300000: false.\nCompared main.suff_outer_par_1 <= 2400000: false.\nCompared main.suff_outer_par_2 <= 19200000: true.\nCompared main.suff_intra_par_3 <= 128: true.\nCompared main.suff_intra_par_4 <= 128: true.\nCompared main.suff_outer_par_5 <= 300000: true.\nCompared main.suff_outer_par_6 <= 2400000: true.\nCompared main.suff_outer_par_7 <= 300000: true.\nCompared main.suff_outer_par_8 <= 2400000: false.\nCompared main.suff_outer_par_9 <= 300000: false.\nCompared main.suff_outer_par_10 <= 480000000: true.\nCompared main.suff_intra_par_11 <= 1600: true.\nCompared main.suff_outer_par_12 <= 300000: false.\nCompared main.suff_intra_par_13 <= 400: true.\nCompared main.suff_outer_par_14 <= 300000: true.\nCompared main.suff_intra_par_15 <= 1200: true.\nruntime: 70672\n\nCompared main.suff_outer_par_0 <= 300000: false.\nCompared main.suff_outer_par_1 <= 2400000: false.\nCompared main.suff_outer_par_2 <= 19200000: true.\nCompared main.suff_intra_par_3 <= 128: true.\nCompared main.suff_intra_par_4 <= 128: true.\nCompared main.suff_outer_par_5 <= 300000: true.\nCompared main.suff_outer_par_6 <= 2400000: true.\nCompared main.suff_outer_par_7 <= 300000: true.\nCompared main.suff_outer_par_8 <= 2400000: false.\nCompared main.suff_outer_par_9 <= 300000: false.\nCompared main.suff_outer_par_10 <= 480000000: true.\nCompared main.suff_intra_par_11 <= 1600: true.\nCompared main.suff_outer_par_12 <= 300000: false.\nCompared main.suff_intra_par_13 <= 400: true.\nCompared main.suff_outer_par_14 <= 300000: true.\nCompared main.suff_intra_par_15 <= 1200: true.\nruntime: 70592\n\nCompared main.suff_outer_par_0 <= 300000: false.\nCompared main.suff_outer_par_1 <= 2400000: false.\nCompared main.suff_outer_par_2 <= 19200000: true.\nCompared main.suff_intra_par_3 <= 128: true.\nCompared main.suff_intra_par_4 <= 128: true.\nCompared main.suff_outer_par_5 <= 300000: true.\nCompared main.suff_outer_par_6 <= 2400000: true.\nCompared main.suff_outer_par_7 <= 300000: true.\nCompared main.suff_outer_par_8 <= 2400000: false.\nCompared main.suff_outer_par_9 <= 300000: false.\nCompared main.suff_outer_par_10 <= 480000000: true.\nCompared main.suff_intra_par_11 <= 1600: true.\nCompared main.suff_outer_par_12 <= 300000: false.\nCompared main.suff_intra_par_13 <= 400: true.\nCompared main.suff_outer_par_14 <= 300000: true.\nCompared main.suff_intra_par_15 <= 1200: true.\nruntime: 70632\n\nCompared main.suff_outer_par_0 <= 300000: false.\nCompared main.suff_outer_par_1 <= 2400000: false.\nCompared main.suff_outer_par_2 <= 19200000: true.\nCompared main.suff_intra_par_3 <= 128: true.\nCompared main.suff_intra_par_4 <= 128: true.\nCompared main.suff_outer_par_5 <= 300000: true.\nCompared main.suff_outer_par_6 <= 2400000: true.\nCompared main.suff_outer_par_7 <= 300000: true.\nCompared main.suff_outer_par_8 <= 2400000: false.\nCompared main.suff_outer_par_9 <= 300000: false.\nCompared main.suff_outer_par_10 <= 480000000: true.\nCompared main.suff_intra_par_11 <= 1600: true.\nCompared main.suff_outer_par_12 <= 300000: false.\nCompared main.suff_intra_par_13 <= 400: true.\nCompared main.suff_outer_par_14 <= 300000: true.\nCompared main.suff_intra_par_15 <= 1200: true.\nruntime: 70681\n\nCompared main.suff_outer_par_0 <= 300000: false.\nCompared main.suff_outer_par_1 <= 2400000: false.\nCompared main.suff_outer_par_2 <= 19200000: true.\nCompared main.suff_intra_par_3 <= 128: true.\nCompared main.suff_intra_par_4 <= 128: true.\nCompared main.suff_outer_par_5 <= 300000: true.\nCompared main.suff_outer_par_6 <= 2400000: true.\nCompared main.suff_outer_par_7 <= 300000: true.\nCompared main.suff_outer_par_8 <= 2400000: false.\nCompared main.suff_outer_par_9 <= 300000: false.\nCompared main.suff_outer_par_10 <= 480000000: true.\nCompared main.suff_intra_par_11 <= 1600: true.\nCompared main.suff_outer_par_12 <= 300000: false.\nCompared main.suff_intra_par_13 <= 400: true.\nCompared main.suff_outer_par_14 <= 300000: true.\nCompared main.suff_intra_par_15 <= 1200: true.\nruntime: 70656\n\nCompared main.suff_outer_par_0 <= 300000: false.\nCompared main.suff_outer_par_1 <= 2400000: false.\nCompared main.suff_outer_par_2 <= 19200000: true.\nCompared main.suff_intra_par_3 <= 128: true.\nCompared main.suff_intra_par_4 <= 128: true.\nCompared main.suff_outer_par_5 <= 300000: true.\nCompared main.suff_outer_par_6 <= 2400000: true.\nCompared main.suff_outer_par_7 <= 300000: true.\nCompared main.suff_outer_par_8 <= 2400000: false.\nCompared main.suff_outer_par_9 <= 300000: false.\nCompared main.suff_outer_par_10 <= 480000000: true.\nCompared main.suff_intra_par_11 <= 1600: true.\nCompared main.suff_outer_par_12 <= 300000: false.\nCompared main.suff_intra_par_13 <= 400: true.\nCompared main.suff_outer_par_14 <= 300000: true.\nCompared main.suff_intra_par_15 <= 1200: true.\nruntime: 70633\n\nCompared main.suff_outer_par_0 <= 300000: false.\nCompared main.suff_outer_par_1 <= 2400000: false.\nCompared main.suff_outer_par_2 <= 19200000: true.\nCompared main.suff_intra_par_3 <= 128: true.\nCompared main.suff_intra_par_4 <= 128: true.\nCompared main.suff_outer_par_5 <= 300000: true.\nCompared main.suff_outer_par_6 <= 2400000: true.\nCompared main.suff_outer_par_7 <= 300000: true.\nCompared main.suff_outer_par_8 <= 2400000: false.\nCompared main.suff_outer_par_9 <= 300000: false.\nCompared main.suff_outer_par_10 <= 480000000: true.\nCompared main.suff_intra_par_11 <= 1600: true.\nCompared main.suff_outer_par_12 <= 300000: false.\nCompared main.suff_intra_par_13 <= 400: true.\nCompared main.suff_outer_par_14 <= 300000: true.\nCompared main.suff_intra_par_15 <= 1200: true.\nruntime: 70698\n\nCompared main.suff_outer_par_0 <= 300000: false.\nCompared main.suff_outer_par_1 <= 2400000: false.\nCompared main.suff_outer_par_2 <= 19200000: true.\nCompared main.suff_intra_par_3 <= 128: true.\nCompared main.suff_intra_par_4 <= 128: true.\nCompared main.suff_outer_par_5 <= 300000: true.\nCompared main.suff_outer_par_6 <= 2400000: true.\nCompared main.suff_outer_par_7 <= 300000: true.\nCompared main.suff_outer_par_8 <= 2400000: false.\nCompared main.suff_outer_par_9 <= 300000: false.\nCompared main.suff_outer_par_10 <= 480000000: true.\nCompared main.suff_intra_par_11 <= 1600: true.\nCompared main.suff_outer_par_12 <= 300000: false.\nCompared main.suff_intra_par_13 <= 400: true.\nCompared main.suff_outer_par_14 <= 300000: true.\nCompared main.suff_intra_par_15 <= 1200: true.\nruntime: 70678\n\nCompared main.suff_outer_par_0 <= 300000: false.\nCompared main.suff_outer_par_1 <= 2400000: false.\nCompared main.suff_outer_par_2 <= 19200000: true.\nCompared main.suff_intra_par_3 <= 128: true.\nCompared main.suff_intra_par_4 <= 128: true.\nCompared main.suff_outer_par_5 <= 300000: true.\nCompared main.suff_outer_par_6 <= 2400000: true.\nCompared main.suff_outer_par_7 <= 300000: true.\nCompared main.suff_outer_par_8 <= 2400000: false.\nCompared main.suff_outer_par_9 <= 300000: false.\nCompared main.suff_outer_par_10 <= 480000000: true.\nCompared main.suff_intra_par_11 <= 1600: true.\nCompared main.suff_outer_par_12 <= 300000: false.\nCompared main.suff_intra_par_13 <= 400: true.\nCompared main.suff_outer_par_14 <= 300000: true.\nCompared main.suff_intra_par_15 <= 1200: true.\nruntime: 70672\n\nCompared main.suff_outer_par_0 <= 300000: false.\nCompared main.suff_outer_par_1 <= 2400000: false.\nCompared main.suff_outer_par_2 <= 19200000: true.\nCompared main.suff_intra_par_3 <= 128: true.\nCompared main.suff_intra_par_4 <= 128: true.\nCompared main.suff_outer_par_5 <= 300000: true.\nCompared main.suff_outer_par_6 <= 2400000: true.\nCompared main.suff_outer_par_7 <= 300000: true.\nCompared main.suff_outer_par_8 <= 2400000: false.\nCompared main.suff_outer_par_9 <= 300000: false.\nCompared main.suff_outer_par_10 <= 480000000: true.\nCompared main.suff_intra_par_11 <= 1600: true.\nCompared main.suff_outer_par_12 <= 300000: false.\nCompared main.suff_intra_par_13 <= 400: true.\nCompared main.suff_outer_par_14 <= 300000: true.\nCompared main.suff_intra_par_15 <= 1200: true.\nruntime: 70629\n\nCompared main.suff_outer_par_0 <= 300000: false.\nCompared main.suff_outer_par_1 <= 2400000: false.\nCompared main.suff_outer_par_2 <= 19200000: true.\nCompared main.suff_intra_par_3 <= 128: true.\nCompared main.suff_intra_par_4 <= 128: true.\nCompared main.suff_outer_par_5 <= 300000: true.\nCompared main.suff_outer_par_6 <= 2400000: true.\nCompared main.suff_outer_par_7 <= 300000: true.\nCompared main.suff_outer_par_8 <= 2400000: false.\nCompared main.suff_outer_par_9 <= 300000: false.\nCompared main.suff_outer_par_10 <= 480000000: true.\nCompared main.suff_intra_par_11 <= 1600: true.\nCompared main.suff_outer_par_12 <= 300000: false.\nCompared main.suff_intra_par_13 <= 400: true.\nCompared main.suff_outer_par_14 <= 300000: true.\nCompared main.suff_intra_par_15 <= 1200: true.\nruntime: 70657\n\nCompared main.suff_outer_par_0 <= 300000: false.\nCompared main.suff_outer_par_1 <= 2400000: false.\nCompared main.suff_outer_par_2 <= 19200000: true.\nCompared main.suff_intra_par_3 <= 128: true.\nCompared main.suff_intra_par_4 <= 128: true.\nCompared main.suff_outer_par_5 <= 300000: true.\nCompared main.suff_outer_par_6 <= 2400000: true.\nCompared main.suff_outer_par_7 <= 300000: true.\nCompared main.suff_outer_par_8 <= 2400000: false.\nCompared main.suff_outer_par_9 <= 300000: false.\nCompared main.suff_outer_par_10 <= 480000000: true.\nCompared main.suff_intra_par_11 <= 1600: true.\nCompared main.suff_outer_par_12 <= 300000: false.\nCompared main.suff_intra_par_13 <= 400: true.\nCompared main.suff_outer_par_14 <= 300000: true.\nCompared main.suff_intra_par_15 <= 1200: true.\nruntime: 70668\n\nCompared main.suff_outer_par_0 <= 300000: false.\nCompared main.suff_outer_par_1 <= 2400000: false.\nCompared main.suff_outer_par_2 <= 19200000: true.\nCompared main.suff_intra_par_3 <= 128: true.\nCompared main.suff_intra_par_4 <= 128: true.\nCompared main.suff_outer_par_5 <= 300000: true.\nCompared main.suff_outer_par_6 <= 2400000: true.\nCompared main.suff_outer_par_7 <= 300000: true.\nCompared main.suff_outer_par_8 <= 2400000: false.\nCompared main.suff_outer_par_9 <= 300000: false.\nCompared main.suff_outer_par_10 <= 480000000: true.\nCompared main.suff_intra_par_11 <= 1600: true.\nCompared main.suff_outer_par_12 <= 300000: false.\nCompared main.suff_intra_par_13 <= 400: true.\nCompared main.suff_outer_par_14 <= 300000: true.\nCompared main.suff_intra_par_15 <= 1200: true.\nruntime: 70639\n\nCompared main.suff_outer_par_0 <= 300000: false.\nCompared main.suff_outer_par_1 <= 2400000: false.\nCompared main.suff_outer_par_2 <= 19200000: true.\nCompared main.suff_intra_par_3 <= 128: true.\nCompared main.suff_intra_par_4 <= 128: true.\nCompared main.suff_outer_par_5 <= 300000: true.\nCompared main.suff_outer_par_6 <= 2400000: true.\nCompared main.suff_outer_par_7 <= 300000: true.\nCompared main.suff_outer_par_8 <= 2400000: false.\nCompared main.suff_outer_par_9 <= 300000: false.\nCompared main.suff_outer_par_10 <= 480000000: true.\nCompared main.suff_intra_par_11 <= 1600: true.\nCompared main.suff_outer_par_12 <= 300000: false.\nCompared main.suff_intra_par_13 <= 400: true.\nCompared main.suff_outer_par_14 <= 300000: true.\nCompared main.suff_intra_par_15 <= 1200: true.\nruntime: 70637\n\nCompared main.suff_outer_par_0 <= 300000: false.\nCompared main.suff_outer_par_1 <= 2400000: false.\nCompared main.suff_outer_par_2 <= 19200000: true.\nCompared main.suff_intra_par_3 <= 128: true.\nCompared main.suff_intra_par_4 <= 128: true.\nCompared main.suff_outer_par_5 <= 300000: true.\nCompared main.suff_outer_par_6 <= 2400000: true.\nCompared main.suff_outer_par_7 <= 300000: true.\nCompared main.suff_outer_par_8 <= 2400000: false.\nCompared main.suff_outer_par_9 <= 300000: false.\nCompared main.suff_outer_par_10 <= 480000000: true.\nCompared main.suff_intra_par_11 <= 1600: true.\nCompared main.suff_outer_par_12 <= 300000: false.\nCompared main.suff_intra_par_13 <= 400: true.\nCompared main.suff_outer_par_14 <= 300000: true.\nCompared main.suff_intra_par_15 <= 1200: true.\nruntime: 70664\n\nPeak memory usage for space 'device': 11520019200 bytes.\n\n"}}}}